[
  {
    "player_id": "00-0039139",
    "player_name": "Jahmyr Gibbs",
    "positions": [
      "RB"
    ],
    "team": "DET",
    "age": 24.2,
    "headshot": "https://static.www.nfl.com/image/upload/f_auto,q_auto/league/hjxk3judytgsxkqiilre"
  },
  {
    "player_id": "00-0038542",
    "player_name": "Bijan Robinson",
    "positions": [
      "RB"
    ],
    "team": "ATL",
    "age": 24.3,
    "headshot": "https://static.www.nfl.com/image/upload/f_auto,q_auto/league/rjaf9auhx3lrktzgwpfb"
  },
  {
    "player_id": "00-0036900",
    "player_name": "Ja'Marr Chase",
    "positions": [
      "WR"
    ],
    "team": "CIN",
    "age": 26.2,
    "headshot": "https://static.www.nfl.com/image/upload/f_auto,q_auto/league/qya3dtjb5kgofcuj2tuw"
  },
  {
    "player_id": "00-0039075",
    "player_name": "Puka Nacua",
    "positions": [
      "WR"
    ],
    "team": "LA",
    "age": 25.0,
    "headshot": "https://static.www.nfl.com/image/upload/f_auto,q_auto/league/zvi4hdm6fywcekfe7ceb"
  },
  {
    "player_id": "00-0038543",
    "player_name": "Jaxon Smith-Njigba",
    "positions": [
      "WR"
    ],
    "team": "SEA",
    "age": 24.3,
    "headshot": "https://static.www.nfl.com/image/upload/f_auto,q_auto/league/jpvhsregfvw46mlyckzj"
  },
  {
    "player_id": "00-0036223",
    "player_name": "Jonathan Taylor",
    "positions": [
      "RB"
    ],
    "team": "IND",
    "age": 27.3,
    "headshot": "https://static.www.nfl.com/image/upload/f_auto,q_auto/league/uwmnrhwtwug0wrgkomjk"
  },
  {
    "player_id": "00-0033280",
    "player_name": "Christian McCaffrey",
    "positions": [
      "RB"
    ],
    "team": "SF",
    "age": 29.9,
    "headshot": "https://static.www.nfl.com/image/upload/f_auto,q_auto/league/resjdwihunsqckohcorj"
  },
  {
    "player_id": "00-0036963",
    "player_name": "Amon-Ra St. Brown",
    "positions": [
      "WR"
    ],
    "team": "DET",
    "age": 26.6,
    "headshot": "https://static.www.nfl.com/image/upload/f_auto,q_auto/league/fd8nwhm6pvxfyzphzl6i"
  },
  {
    "player_id": "00-0036358",
    "player_name": "CeeDee Lamb",
    "positions": [
      "WR"
    ],
    "team": "DAL",
    "age": 27.1,
    "headshot": "https://static.www.nfl.com/image/upload/f_auto,q_auto/league/ijxzvtumjhqu3zva1bwc"
  },
  {
    "player_id": "00-0037248",
    "player_name": "James Cook III",
    "positions": [
      "RB"
    ],
    "team": "BUF",
    "age": 26.6,
    "headshot": "https://static.www.nfl.com/image/upload/f_auto,q_auto/league/anjbznqb9i21wzcgrtbs"
  },
  {
    "player_id": "00-0037238",
    "player_name": "Drake London",
    "positions": [
      "WR"
    ],
    "team": "ATL",
    "age": 24.8,
    "headshot": "https://static.www.nfl.com/image/upload/f_auto,q_auto/league/np91pvk7mczra1iyjkmo"
  },
  {
    "player_id": "00-0036322",
    "player_name": "Justin Jefferson",
    "positions": [
      "WR"
    ],
    "team": "MIN",
    "age": 26.9,
    "headshot": "https://static.www.nfl.com/image/upload/f_auto,q_auto/league/f0ccavu3ppzcs51e1cuv"
  },
  {
    "player_id": "00-0036554",
    "player_name": "Nico Collins",
    "positions": [
      "WR"
    ],
    "team": "HOU",
    "age": 27.2,
    "headshot": "https://static.www.nfl.com/image/upload/f_auto,q_auto/league/osmqyvmib3pssxi6cyic"
  },
  {
    "player_id": "00-0039337",
    "player_name": "Malik Nabers",
    "positions": [
      "WR"
    ],
    "team": "NYG",
    "age": 22.8,
    "headshot": "https://static.www.nfl.com/image/upload/f_auto,q_auto/league/w3edoyyuomqlovvp9ixc"
  },
  {
    "player_id": "00-0040122",
    "player_name": "Ashton Jeanty",
    "positions": [
      "RB"
    ],
    "team": "LV",
    "age": 22.5,
    "headshot": "https://static.www.nfl.com/image/upload/f_auto,q_auto/league/syspis1mntov9kgspb7r"
  },
  {
    "player_id": "00-0034844",
    "player_name": "Saquon Barkley",
    "positions": [
      "RB"
    ],
    "team": "PHI",
    "age": 29.3,
    "headshot": "https://static.www.nfl.com/image/upload/f_auto,q_auto/league/ern1nbhivkmwkg82c7v1"
  },
  {
    "player_id": "00-0039040",
    "player_name": "De'Von Achane",
    "positions": [
      "RB"
    ],
    "team": "MIA",
    "age": 24.6,
    "headshot": "https://static.www.nfl.com/image/upload/f_auto,q_auto/league/xk1xwio0bryfxo1ylweu"
  },
  {
    "player_id": "00-0032764",
    "player_name": "Derrick Henry",
    "positions": [
      "RB"
    ],
    "team": "BAL",
    "age": 32.4,
    "headshot": "https://static.www.nfl.com/image/upload/f_auto,q_auto/league/jxtikemnvpkw9r0ex2wv"
  },
  {
    "player_id": "00-0037247",
    "player_name": "George Pickens",
    "positions": [
      "WR"
    ],
    "team": "DAL",
    "age": 25.2,
    "headshot": "https://static.www.nfl.com/image/upload/f_auto,q_auto/league/cbpyykoguf7rsxezqzvk"
  },
  {
    "player_id": "00-0039067",
    "player_name": "Rashee Rice",
    "positions": [
      "WR"
    ],
    "team": "KC",
    "age": 26.1,
    "headshot": "https://static.www.nfl.com/image/upload/f_auto,q_auto/league/iy0uidp9wokc6a7u8lwq"
  },
  {
    "player_id": "00-0037744",
    "player_name": "Trey McBride",
    "positions": [
      "TE"
    ],
    "team": "ARI",
    "age": 26.5,
    "headshot": "https://static.www.nfl.com/image/upload/f_auto,q_auto/league/vd7av3vdfs6q7ncjogac"
  },
  {
    "player_id": "00-0039338",
    "player_name": "Brock Bowers",
    "positions": [
      "TE"
    ],
    "team": "LV",
    "age": 23.4,
    "headshot": "https://static.www.nfl.com/image/upload/f_auto,q_auto/league/uzp2ffi0lomamxofsrhy"
  },
  {
    "player_id": "00-0034857",
    "player_name": "Josh Allen",
    "positions": [
      "QB"
    ],
    "team": "BUF",
    "age": 30.0,
    "headshot": "https://static.www.nfl.com/image/upload/f_auto,q_auto/league/servs1fpsynfxep4rz2z"
  },
  {
    "player_id": "00-0040666",
    "player_name": "Omarion Hampton",
    "positions": [
      "RB"
    ],
    "team": "LAC",
    "age": 23.2,
    "headshot": "https://static.www.nfl.com/image/upload/f_auto,q_auto/league/ck7xcbwuka7wu2zwhssk"
  },
  {
    "player_id": "00-0035676",
    "player_name": "A.J. Brown",
    "positions": [
      "WR"
    ],
    "team": "PHI",
    "age": 28.9,
    "headshot": "https://static.www.nfl.com/image/private/f_auto,q_auto/league/a014sgzctarbvhwb35lw"
  },
  {
    "player_id": "00-0037239",
    "player_name": "Chris Olave",
    "positions": [
      "WR"
    ],
    "team": "NO",
    "age": 25.9,
    "headshot": "https://static.www.nfl.com/image/upload/f_auto,q_auto/league/vrrmyvpvujynckag9jop"
  },
  {
    "player_id": "00-0038134",
    "player_name": "Kenneth Walker III",
    "positions": [
      "RB"
    ],
    "team": "KC",
    "age": 25.6,
    "headshot": "https://static.www.nfl.com/image/upload/f_auto,q_auto/league/mnzsnemdzbey5hbahdhk"
  },
  {
    "player_id": "00-0038597",
    "player_name": "Chase Brown",
    "positions": [
      "RB"
    ],
    "team": "CIN",
    "age": 26.2,
    "headshot": "https://static.www.nfl.com/image/upload/f_auto,q_auto/league/pv3sq3uzosixxexbznq5"
  },
  {
    "player_id": "00-0034796",
    "player_name": "Lamar Jackson",
    "positions": [
      "QB"
    ],
    "team": "BAL",
    "age": 29.4,
    "headshot": "https://static.www.nfl.com/image/upload/f_auto,q_auto/league/cruqs6qpbykh7a2whd7p"
  },
  {
    "player_id": "00-0035700",
    "player_name": "Josh Jacobs",
    "positions": [
      "RB"
    ],
    "team": "GB",
    "age": 28.3,
    "headshot": "https://static.www.nfl.com/image/upload/f_auto,q_auto/league/drtobqw2mk7yw3edjgwo"
  },
  {
    "player_id": "00-0036410",
    "player_name": "Tee Higgins",
    "positions": [
      "WR"
    ],
    "team": "CIN",
    "age": 27.3,
    "headshot": "https://static.www.nfl.com/image/upload/f_auto,q_auto/league/flr9f8oqigbyroeaubxb"
  },
  {
    "player_id": "00-0039851",
    "player_name": "Drake Maye",
    "positions": [
      "QB"
    ],
    "team": "NE",
    "age": 23.7,
    "headshot": "https://static.www.nfl.com/image/upload/f_auto,q_auto/league/oyap81gtzcvnfmripis1"
  },
  {
    "player_id": "00-0040124",
    "player_name": "Tetairoa McMillan",
    "positions": [
      "WR"
    ],
    "team": "CAR",
    "age": 23.1,
    "headshot": "https://static.www.nfl.com/image/upload/f_auto,q_auto/league/hokqp6gl5xujtlqwecg8"
  },
  {
    "player_id": "LOV121782",
    "player_name": "Jeremiyah Love",
    "positions": [
      "RB"
    ],
    "team": "ARI",
    "age": 21.0,
    "headshot": null
  },
  {
    "player_id": "00-0031381",
    "player_name": "Davante Adams",
    "positions": [
      "WR"
    ],
    "team": "LA",
    "age": 33.4,
    "headshot": "https://static.www.nfl.com/image/upload/f_auto,q_auto/league/qtonvcqpixixqhc6lhnc"
  },
  {
    "player_id": "00-0037840",
    "player_name": "Kyren Williams",
    "positions": [
      "RB"
    ],
    "team": "LA",
    "age": 25.7,
    "headshot": "https://static.www.nfl.com/image/upload/f_auto,q_auto/league/smsyrjrwy0lf0hu9hkvg"
  },
  {
    "player_id": "00-0038996",
    "player_name": "Tucker Kraft",
    "positions": [
      "TE"
    ],
    "team": "GB",
    "age": 25.5,
    "headshot": "https://static.www.nfl.com/image/upload/f_auto,q_auto/league/yr6nj1zqaqg6nbdnxu3q"
  },
  {
    "player_id": "00-0036997",
    "player_name": "Javonte Williams",
    "positions": [
      "RB"
    ],
    "team": "DAL",
    "age": 26.1,
    "headshot": "https://static.www.nfl.com/image/upload/f_auto,q_auto/league/hwzske22c4wrlf27qrih"
  },
  {
    "player_id": "00-0036442",
    "player_name": "Joe Burrow",
    "positions": [
      "QB"
    ],
    "team": "CIN",
    "age": 29.4,
    "headshot": "https://static.www.nfl.com/image/upload/f_auto,q_auto/league/gnnvcgui1cijybukk2w7"
  },
  {
    "player_id": "00-0038120",
    "player_name": "Breece Hall",
    "positions": [
      "RB"
    ],
    "team": "NYJ",
    "age": 25.0,
    "headshot": "https://static.www.nfl.com/image/upload/f_auto,q_auto/league/m3dviruymtm2wl2zcpmr"
  },
  {
    "player_id": "00-0039064",
    "player_name": "Zay Flowers",
    "positions": [
      "WR"
    ],
    "team": "BAL",
    "age": 25.7,
    "headshot": "https://static.www.nfl.com/image/upload/f_auto,q_auto/league/sqqh8gmxdpo55qwpsszj"
  },
  {
    "player_id": "00-0036973",
    "player_name": "Travis Etienne Jr.",
    "positions": [
      "RB"
    ],
    "team": "NO",
    "age": 27.3,
    "headshot": "https://static.www.nfl.com/image/upload/f_auto,q_auto/league/gc0iljgj34piecyfueyd"
  },
  {
    "player_id": "00-0036912",
    "player_name": "DeVonta Smith",
    "positions": [
      "WR"
    ],
    "team": "PHI",
    "age": 27.5,
    "headshot": "https://static.www.nfl.com/image/upload/f_auto,q_auto/league/vj2fz8veorg1k5qthnjm"
  },
  {
    "player_id": "00-0035659",
    "player_name": "Terry McLaurin",
    "positions": [
      "WR"
    ],
    "team": "WAS",
    "age": 30.7,
    "headshot": "https://static.www.nfl.com/image/upload/f_auto,q_auto/league/wokz1etv1wj1vhbmvxgs"
  },
  {
    "player_id": "00-0040126",
    "player_name": "Colston Loveland",
    "positions": [
      "TE"
    ],
    "team": "CHI",
    "age": 22.1,
    "headshot": "https://static.www.nfl.com/image/upload/f_auto,q_auto/league/tyjb6vfug7gaunvcune3"
  },
  {
    "player_id": "00-0037240",
    "player_name": "Jameson Williams",
    "positions": [
      "WR"
    ],
    "team": "DET",
    "age": 25.1,
    "headshot": "https://static.www.nfl.com/image/upload/f_auto,q_auto/league/gpjarmglg1jhwq5wr1uu"
  },
  {
    "player_id": "00-0037740",
    "player_name": "Garrett Wilson",
    "positions": [
      "WR"
    ],
    "team": "NYJ",
    "age": 25.8,
    "headshot": "https://static.www.nfl.com/image/upload/f_auto,q_auto/league/kbijsheobhwej7lh8mvf"
  },
  {
    "player_id": "00-0040129",
    "player_name": "Emeka Egbuka",
    "positions": [
      "WR"
    ],
    "team": "TB",
    "age": 23.6,
    "headshot": "https://static.www.nfl.com/image/upload/f_auto,q_auto/league/qolqqtwamffi0pi4np7h"
  },
  {
    "player_id": "00-0039915",
    "player_name": "Ladd McConkey",
    "positions": [
      "WR"
    ],
    "team": "LAC",
    "age": 24.5,
    "headshot": "https://static.www.nfl.com/image/upload/f_auto,q_auto/league/qsvdiebsa34jtkcrjpju"
  },
  {
    "player_id": "00-0036613",
    "player_name": "Jaylen Waddle",
    "positions": [
      "WR"
    ],
    "team": "DEN",
    "age": 27.5,
    "headshot": "https://static.www.nfl.com/image/upload/f_auto,q_auto/league/dsxd2zcqm42wsv4ewtfc"
  },
  {
    "player_id": "00-0039361",
    "player_name": "Bucky Irving",
    "positions": [
      "RB"
    ],
    "team": "TB",
    "age": 23.7,
    "headshot": "https://static.www.nfl.com/image/upload/f_auto,q_auto/league/hmgpumoxwhvrrkcjuuuw"
  },
  {
    "player_id": "00-0039910",
    "player_name": "Jayden Daniels",
    "positions": [
      "QB"
    ],
    "team": "WAS",
    "age": 25.4,
    "headshot": "https://static.www.nfl.com/image/upload/f_auto,q_auto/league/vrdweg39v1ay4zoc0lgp"
  },
  {
    "player_id": "00-0040735",
    "player_name": "Luther Burden III",
    "positions": [
      "WR"
    ],
    "team": "CHI",
    "age": 22.4,
    "headshot": "https://static.www.nfl.com/image/upload/f_auto,q_auto/league/iyuwdz7pbowdkwzq2tg5"
  },
  {
    "player_id": "00-0038124",
    "player_name": "Christian Watson",
    "positions": [
      "WR"
    ],
    "team": "GB",
    "age": 27.0,
    "headshot": "https://static.www.nfl.com/image/upload/f_auto,q_auto/league/syljognztlbghfeqyqn1"
  },
  {
    "player_id": "00-0036389",
    "player_name": "Jalen Hurts",
    "positions": [
      "QB"
    ],
    "team": "PHI",
    "age": 27.8,
    "headshot": "https://static.www.nfl.com/image/upload/f_auto,q_auto/league/c47i9v6gmokkun9cat9s"
  },
  {
    "player_id": "00-0040715",
    "player_name": "Cam Skattebo",
    "positions": [
      "RB"
    ],
    "team": "NYG",
    "age": 24.3,
    "headshot": "https://static.www.nfl.com/image/upload/f_auto,q_auto/league/vnftthkbvw7ucsqtqjpq"
  },
  {
    "player_id": "00-0040734",
    "player_name": "TreVeyon Henderson",
    "positions": [
      "RB"
    ],
    "team": "NE",
    "age": 23.6,
    "headshot": "https://static.www.nfl.com/image/upload/f_auto,q_auto/league/cfcux3dnfmbmz3qzrnco"
  },
  {
    "player_id": "00-0031408",
    "player_name": "Mike Evans",
    "positions": [
      "WR"
    ],
    "team": "SF",
    "age": 32.7,
    "headshot": "https://static.www.nfl.com/image/upload/f_auto,q_auto/league/yaxorbdsvk1ucfuiyrkj"
  },
  {
    "player_id": "00-0035685",
    "player_name": "David Montgomery",
    "positions": [
      "RB"
    ],
    "team": "HOU",
    "age": 28.9,
    "headshot": "https://static.www.nfl.com/image/upload/f_auto,q_auto/league/xeb6fq4zimgkksq7uari"
  },
  {
    "player_id": "00-0040784",
    "player_name": "Quinshon Judkins",
    "positions": [
      "RB"
    ],
    "team": "CLE",
    "age": 22.6,
    "headshot": "https://static.www.nfl.com/image/upload/f_auto,q_auto/league/ojtce2im0wp2ltyel0vc"
  },
  {
    "player_id": "00-0036275",
    "player_name": "D'Andre Swift",
    "positions": [
      "RB"
    ],
    "team": "CHI",
    "age": 27.3,
    "headshot": "https://static.www.nfl.com/image/upload/f_auto,q_auto/league/owpmwzoilitcodc6cmxo"
  },
  {
    "player_id": "00-0034827",
    "player_name": "DJ Moore",
    "positions": [
      "WR"
    ],
    "team": "BUF",
    "age": 29.1,
    "headshot": "https://static.www.nfl.com/image/upload/f_auto,q_auto/league/qphturmeiifnqrnf5pax"
  },
  {
    "player_id": "00-0039919",
    "player_name": "Rome Odunze",
    "positions": [
      "WR"
    ],
    "team": "CHI",
    "age": 24.0,
    "headshot": "https://static.www.nfl.com/image/upload/f_auto,q_auto/league/yqjdhpsno75du0n72u4w"
  },
  {
    "player_id": "00-0040719",
    "player_name": "Bhayshul Tuten",
    "positions": [
      "RB"
    ],
    "team": "JAX",
    "age": 24.3,
    "headshot": "https://static.www.nfl.com/image/upload/f_auto,q_auto/league/uf6bidyfjeemrlgsibiz"
  },
  {
    "player_id": "TAT143045",
    "player_name": "Carnell Tate",
    "positions": [
      "WR"
    ],
    "team": "TEN",
    "age": 21.3,
    "headshot": null
  },
  {
    "player_id": "00-0040128",
    "player_name": "Tyler Warren",
    "positions": [
      "TE"
    ],
    "team": "IND",
    "age": 24.0,
    "headshot": "https://static.www.nfl.com/image/upload/f_auto,q_auto/league/jt2almbzdk0kbha39otb"
  },
  {
    "player_id": "PRI206342",
    "player_name": "Jadarian Price",
    "positions": [
      "RB"
    ],
    "team": "SEA",
    "age": 22.6,
    "headshot": null
  },
  {
    "player_id": "00-0036355",
    "player_name": "Justin Herbert",
    "positions": [
      "QB"
    ],
    "team": "LAC",
    "age": 28.2,
    "headshot": "https://static.www.nfl.com/image/upload/f_auto,q_auto/league/s1oelyaroiaalgilbeqk"
  },
  {
    "player_id": "00-0040691",
    "player_name": "Jaxson Dart",
    "positions": [
      "QB"
    ],
    "team": "NYG",
    "age": 23.0,
    "headshot": "https://static.www.nfl.com/image/upload/f_auto,q_auto/league/n6uymxssgiicjmxkzxoc"
  },
  {
    "player_id": "00-0037664",
    "player_name": "Alec Pierce",
    "positions": [
      "WR"
    ],
    "team": "IND",
    "age": 26.0,
    "headshot": "https://static.www.nfl.com/image/upload/f_auto,q_auto/league/zeghrjc8rir3r3zi6det"
  },
  {
    "player_id": "TYS405541",
    "player_name": "Jordyn Tyson",
    "positions": [
      "WR"
    ],
    "team": "NO",
    "age": 21.8,
    "headshot": null
  },
  {
    "player_id": "00-0039918",
    "player_name": "Caleb Williams",
    "positions": [
      "QB"
    ],
    "team": "CHI",
    "age": 24.5,
    "headshot": "https://static.www.nfl.com/image/upload/f_auto,q_auto/league/h4qs11kutwiw7whekmyt"
  },
  {
    "player_id": "00-0035640",
    "player_name": "DK Metcalf",
    "positions": [
      "WR"
    ],
    "team": "PIT",
    "age": 28.4,
    "headshot": "https://static.www.nfl.com/image/upload/f_auto,q_auto/league/tknefloqsleltfmslj2y"
  },
  {
    "player_id": "00-0037228",
    "player_name": "Jaylen Warren",
    "positions": [
      "RB"
    ],
    "team": "PIT",
    "age": 27.5,
    "headshot": "https://static.www.nfl.com/image/upload/f_auto,q_auto/league/f3txbqdarbabqtq4sx98"
  },
  {
    "player_id": "00-0039849",
    "player_name": "Marvin Harrison Jr.",
    "positions": [
      "WR"
    ],
    "team": "ARI",
    "age": 23.8,
    "headshot": "https://static.www.nfl.com/image/upload/f_auto,q_auto/league/hwpoo1icpnh8emjvqaii"
  },
  {
    "player_id": "00-0036971",
    "player_name": "Trevor Lawrence",
    "positions": [
      "QB"
    ],
    "team": "JAX",
    "age": 26.6,
    "headshot": "https://static.www.nfl.com/image/upload/f_auto,q_auto/league/d75srntioly7fq0z8vip"
  },
  {
    "player_id": "00-0036555",
    "player_name": "Chuba Hubbard",
    "positions": [
      "RB"
    ],
    "team": "CAR",
    "age": 26.9,
    "headshot": "https://static.www.nfl.com/image/upload/f_auto,q_auto/league/pjgml85ghq7oa48dctn7"
  },
  {
    "player_id": "00-0034348",
    "player_name": "Courtland Sutton",
    "positions": [
      "WR"
    ],
    "team": "DEN",
    "age": 30.6,
    "headshot": "https://static.www.nfl.com/image/upload/f_auto,q_auto/league/r2sr6cbma4c7wc3isejj"
  },
  {
    "player_id": "LEM694125",
    "player_name": "Makai Lemon",
    "positions": [
      "WR"
    ],
    "team": "PHI",
    "age": 22.0,
    "headshot": null
  },
  {
    "player_id": "00-0040663",
    "player_name": "Harold Fannin Jr.",
    "positions": [
      "TE"
    ],
    "team": "CLE",
    "age": 21.8,
    "headshot": "https://static.www.nfl.com/image/upload/f_auto,q_auto/league/fxublmpnxx9uggsddwik"
  },
  {
    "player_id": "00-0036139",
    "player_name": "Rico Dowdle",
    "positions": [
      "RB"
    ],
    "team": "PIT",
    "age": 27.9,
    "headshot": "https://static.www.nfl.com/image/upload/f_auto,q_auto/league/cvnrzndsiaojvvxz8vo5"
  },
  {
    "player_id": "00-0039738",
    "player_name": "Blake Corum",
    "positions": [
      "RB"
    ],
    "team": "LA",
    "age": 25.5,
    "headshot": "https://static.www.nfl.com/image/upload/f_auto,q_auto/league/gytdgnrjj3jk8rlfxz85"
  },
  {
    "player_id": "00-0039065",
    "player_name": "Sam LaPorta",
    "positions": [
      "TE"
    ],
    "team": "DET",
    "age": 25.3,
    "headshot": "https://static.www.nfl.com/image/upload/f_auto,q_auto/league/qfcy3taaoage00rrl0cc"
  },
  {
    "player_id": "00-0033077",
    "player_name": "Dak Prescott",
    "positions": [
      "QB"
    ],
    "team": "DAL",
    "age": 32.8,
    "headshot": "https://static.www.nfl.com/image/upload/f_auto,q_auto/league/blixemm3s9sa4gmqk5yn"
  },
  {
    "player_id": "00-0040236",
    "player_name": "Kyle Monangai",
    "positions": [
      "RB"
    ],
    "team": "CHI",
    "age": 24.0,
    "headshot": "https://static.www.nfl.com/image/upload/f_auto,q_auto/league/cici2wf1walmoluhe95i"
  },
  {
    "player_id": "00-0036875",
    "player_name": "Rhamondre Stevenson",
    "positions": [
      "RB"
    ],
    "team": "NE",
    "age": 28.2,
    "headshot": "https://static.www.nfl.com/image/upload/f_auto,q_auto/league/ed09migntlyy8ntgvcu1"
  },
  {
    "player_id": "00-0039893",
    "player_name": "Brian Thomas Jr.",
    "positions": [
      "WR"
    ],
    "team": "JAX",
    "age": 23.6,
    "headshot": "https://static.www.nfl.com/image/upload/f_auto,q_auto/league/plnekkriys4cm11rnxwl"
  },
  {
    "player_id": "00-0040730",
    "player_name": "RJ Harvey",
    "positions": [
      "RB"
    ],
    "team": "DEN",
    "age": 25.3,
    "headshot": "https://static.www.nfl.com/image/upload/f_auto,q_auto/league/i1qxzydetb2orrynzvzk"
  },
  {
    "player_id": "00-0035261",
    "player_name": "Tony Pollard",
    "positions": [
      "RB"
    ],
    "team": "TEN",
    "age": 29.1,
    "headshot": "https://static.www.nfl.com/image/upload/f_auto,q_auto/league/dvpdczetkdhrqpm8izmd"
  },
  {
    "player_id": "00-0036970",
    "player_name": "Kyle Pitts Sr.",
    "positions": [
      "TE"
    ],
    "team": "ATL",
    "age": 25.6,
    "headshot": "https://static.www.nfl.com/image/upload/f_auto,q_auto/league/tbec213me3pszzszecqo"
  },
  {
    "player_id": "00-0038559",
    "player_name": "Michael Wilson",
    "positions": [
      "WR"
    ],
    "team": "ARI",
    "age": 26.2,
    "headshot": "https://static.www.nfl.com/image/upload/f_auto,q_auto/league/yc8awtck004bz2a5oeb8"
  },
  {
    "player_id": "00-0036158",
    "player_name": "J.K. Dobbins",
    "positions": [
      "RB"
    ],
    "team": "DEN",
    "age": 27.4,
    "headshot": "https://static.www.nfl.com/image/upload/f_auto,q_auto/league/cevotvl3ho5h1mioruyg"
  },
  {
    "player_id": "00-0033921",
    "player_name": "Chris Godwin Jr.",
    "positions": [
      "WR"
    ],
    "team": "TB",
    "age": 30.2,
    "headshot": "https://static.www.nfl.com/image/upload/f_auto,q_auto/league/ilkheljdx4hbjpisulke"
  },
  {
    "player_id": "00-0037834",
    "player_name": "Brock Purdy",
    "positions": [
      "QB"
    ],
    "team": "SF",
    "age": 26.4,
    "headshot": "https://static.www.nfl.com/image/upload/f_auto,q_auto/league/xykdxnvxpf9pobxvkjfj"
  },
  {
    "player_id": "00-0038994",
    "player_name": "Jordan Addison",
    "positions": [
      "WR"
    ],
    "team": "MIN",
    "age": 24.3,
    "headshot": "https://static.www.nfl.com/image/upload/f_auto,q_auto/league/s2ey8g5memyqvxc52uzy"
  },
  {
    "player_id": "00-0038933",
    "player_name": "Dalton Kincaid",
    "positions": [
      "TE"
    ],
    "team": "BUF",
    "age": 26.6,
    "headshot": "https://static.www.nfl.com/image/upload/f_auto,q_auto/league/zwkeaiecuyafkidllebz"
  },
  {
    "player_id": "00-0038606",
    "player_name": "Parker Washington",
    "positions": [
      "WR"
    ],
    "team": "JAX",
    "age": 24.2,
    "headshot": "https://static.www.nfl.com/image/upload/f_auto,q_auto/league/sqgxayp6nrrpvwonksdm"
  },
  {
    "player_id": "00-0040242",
    "player_name": "Jacory Croskey-Merritt",
    "positions": [
      "RB"
    ],
    "team": "WAS",
    "age": 25.1,
    "headshot": "https://static.www.nfl.com/image/upload/f_auto,q_auto/league/tklzj7zzve1t4z2hhr1g"
  },
  {
    "player_id": "00-0033873",
    "player_name": "Patrick Mahomes II",
    "positions": [
      "QB"
    ],
    "team": "KC",
    "age": 30.7,
    "headshot": "https://static.www.nfl.com/image/upload/f_auto,q_auto/league/iireqbn32cpg9fn4sfy7"
  },
  {
    "player_id": "00-0026498",
    "player_name": "Matthew Stafford",
    "positions": [
      "QB"
    ],
    "team": "LA",
    "age": 38.3,
    "headshot": "https://static.www.nfl.com/image/upload/f_auto,q_auto/league/svxl2pk2cuqf26zrhii4"
  },
  {
    "player_id": "00-0039732",
    "player_name": "Bo Nix",
    "positions": [
      "QB"
    ],
    "team": "DEN",
    "age": 26.2,
    "headshot": "https://static.www.nfl.com/image/upload/f_auto,q_auto/league/igirshmrr6lqtxcpxsea"
  },
  {
    "player_id": "00-0039916",
    "player_name": "Ricky Pearsall",
    "positions": [
      "WR"
    ],
    "team": "SF",
    "age": 25.7,
    "headshot": "https://static.www.nfl.com/image/upload/f_auto,q_auto/league/ko3lwlcfkxaykcspt4nw"
  },
  {
    "player_id": "00-0034960",
    "player_name": "Jakobi Meyers",
    "positions": [
      "WR"
    ],
    "team": "JAX",
    "age": 29.5,
    "headshot": "https://static.www.nfl.com/image/upload/f_auto,q_auto/league/qui5ajbevlk7pfjpcufz"
  },
  {
    "player_id": "00-0038544",
    "player_name": "Quentin Johnston",
    "positions": [
      "WR"
    ],
    "team": "LAC",
    "age": 24.7,
    "headshot": "https://static.www.nfl.com/image/upload/f_auto,q_auto/league/bpzdpin1xp1kjxmbkq6d"
  },
  {
    "player_id": "00-0040189",
    "player_name": "Oronde Gadsden II",
    "positions": [
      "TE"
    ],
    "team": "LAC",
    "age": 22.9,
    "headshot": "https://static.www.nfl.com/image/upload/f_auto,q_auto/league/r8b4oghjwhw8x9nv1wbs"
  },
  {
    "player_id": "00-0033288",
    "player_name": "George Kittle",
    "positions": [
      "TE"
    ],
    "team": "SF",
    "age": 32.6,
    "headshot": "https://static.www.nfl.com/image/upload/f_auto,q_auto/league/ztz3xqjaqgok9m4nylgs"
  },
  {
    "player_id": "00-0033293",
    "player_name": "Aaron Jones Sr.",
    "positions": [
      "RB"
    ],
    "team": "MIN",
    "age": 31.5,
    "headshot": "https://static.www.nfl.com/image/upload/f_auto,q_auto/league/bktkfvgfwujkdbzkcfim"
  },
  {
    "player_id": "00-0033106",
    "player_name": "Jared Goff",
    "positions": [
      "QB"
    ],
    "team": "DET",
    "age": 31.6,
    "headshot": "https://static.www.nfl.com/image/upload/f_auto,q_auto/league/yggfwr4ak4po9byj0qor"
  },
  {
    "player_id": "00-0035228",
    "player_name": "Kyler Murray",
    "positions": [
      "QB"
    ],
    "team": "MIN",
    "age": 28.8,
    "headshot": "https://static.www.nfl.com/image/upload/f_auto,q_auto/league/flezsremqighwuiyu77f"
  },
  {
    "player_id": "00-0034351",
    "player_name": "Dallas Goedert",
    "positions": [
      "TE"
    ],
    "team": "PHI",
    "age": 31.4,
    "headshot": "https://static.www.nfl.com/image/upload/f_auto,q_auto/league/a6ljhwvkehvyiufdx3d1"
  },
  {
    "player_id": "00-0039146",
    "player_name": "Jayden Reed",
    "positions": [
      "WR"
    ],
    "team": "GB",
    "age": 26.1,
    "headshot": "https://static.www.nfl.com/image/upload/f_auto,q_auto/league/blh2tfg9qjthqo2g6ot4"
  },
  {
    "player_id": "00-0036252",
    "player_name": "Michael Pittman Jr.",
    "positions": [
      "WR"
    ],
    "team": "PIT",
    "age": 28.6,
    "headshot": "https://static.www.nfl.com/image/upload/f_auto,q_auto/league/z78xpye9hing1e7wke8b"
  },
  {
    "player_id": "00-0037525",
    "player_name": "Jordan Mason",
    "positions": [
      "RB"
    ],
    "team": "MIN",
    "age": 27.0,
    "headshot": "https://static.www.nfl.com/image/upload/f_auto,q_auto/league/ixykwytfrfz1cdxlhj5w"
  },
  {
    "player_id": "00-0036264",
    "player_name": "Jordan Love",
    "positions": [
      "QB"
    ],
    "team": "GB",
    "age": 27.5,
    "headshot": "https://static.www.nfl.com/image/upload/f_auto,q_auto/league/uneiwen9drvci9ahuebp"
  },
  {
    "player_id": "00-0039165",
    "player_name": "Zach Charbonnet",
    "positions": [
      "RB"
    ],
    "team": "SEA",
    "age": 25.4,
    "headshot": "https://static.www.nfl.com/image/upload/f_auto,q_auto/league/jqbzg5e8pdltbnb7hc8p"
  },
  {
    "player_id": "00-0030506",
    "player_name": "Travis Kelce",
    "positions": [
      "TE"
    ],
    "team": "KC",
    "age": 36.6,
    "headshot": "https://static.www.nfl.com/image/upload/f_auto,q_auto/league/ebc5j60djpinc9elvlc5"
  },
  {
    "player_id": "00-0040130",
    "player_name": "Jayden Higgins",
    "positions": [
      "WR"
    ],
    "team": "HOU",
    "age": 23.4,
    "headshot": "https://static.www.nfl.com/image/upload/f_auto,q_auto/league/wrdw1u4onrmfuuluuipk"
  },
  {
    "player_id": "00-0037263",
    "player_name": "Tyler Allgeier",
    "positions": [
      "RB"
    ],
    "team": "ARI",
    "age": 26.1,
    "headshot": "https://static.www.nfl.com/image/upload/f_auto,q_auto/league/buwaomfsz4y6orgb0cyg"
  },
  {
    "player_id": "00-0037256",
    "player_name": "Rachaad White",
    "positions": [
      "RB"
    ],
    "team": "WAS",
    "age": 27.3,
    "headshot": "https://static.www.nfl.com/image/upload/f_auto,q_auto/league/sxugbms8ketvgmilnlu3"
  },
  {
    "player_id": "00-0040743",
    "player_name": "Tyler Shough",
    "positions": [
      "QB"
    ],
    "team": "NO",
    "age": 26.6,
    "headshot": "https://static.www.nfl.com/image/upload/f_auto,q_auto/league/wsrkib8qgwtb2t2ugaru"
  },
  {
    "player_id": "00-0040583",
    "player_name": "Woody Marks",
    "positions": [
      "RB"
    ],
    "team": "HOU",
    "age": 25.4,
    "headshot": "https://static.www.nfl.com/image/upload/f_auto,q_auto/league/pwvxisrnjitkkghkfcn3"
  },
  {
    "player_id": "00-0034855",
    "player_name": "Baker Mayfield",
    "positions": [
      "QB"
    ],
    "team": "TB",
    "age": 31.1,
    "headshot": "https://static.www.nfl.com/image/upload/f_auto,q_auto/league/i2uufyghiphx4oihgucm"
  },
  {
    "player_id": "00-0038041",
    "player_name": "Jake Ferguson",
    "positions": [
      "TE"
    ],
    "team": "DAL",
    "age": 27.3,
    "headshot": "https://static.www.nfl.com/image/upload/f_auto,q_auto/league/ebdz1yf8ky2mscdvyv1v"
  },
  {
    "player_id": "00-0038128",
    "player_name": "Malik Willis",
    "positions": [
      "QB"
    ],
    "team": "MIA",
    "age": 27.0,
    "headshot": "https://static.www.nfl.com/image/upload/f_auto,q_auto/league/hsnetccy7bquili3gcqq"
  },
  {
    "player_id": "00-0036919",
    "player_name": "Kenneth Gainwell",
    "positions": [
      "RB"
    ],
    "team": "TB",
    "age": 27.2,
    "headshot": "https://static.www.nfl.com/image/upload/f_auto,q_auto/league/f74x1ywy7oo5kq81vblh"
  },
  {
    "player_id": "00-0038117",
    "player_name": "Wan'Dale Robinson",
    "positions": [
      "WR"
    ],
    "team": "TEN",
    "age": 25.4,
    "headshot": "https://static.www.nfl.com/image/upload/f_auto,q_auto/league/yzcvyhmilvxedfjfjglc"
  },
  {
    "player_id": "00-0038611",
    "player_name": "Chris Rodriguez Jr.",
    "positions": [
      "RB"
    ],
    "team": "JAX",
    "age": 26.6,
    "headshot": "https://static.www.nfl.com/image/upload/f_auto,q_auto/league/z5nbh1nza9je683o17h1"
  },
  {
    "player_id": "00-0037816",
    "player_name": "Romeo Doubs",
    "positions": [
      "WR"
    ],
    "team": "NE",
    "age": 26.1,
    "headshot": "https://static.www.nfl.com/image/upload/f_auto,q_auto/league/ov2llp1bfetznmngqybi"
  },
  {
    "player_id": "00-0039894",
    "player_name": "Xavier Worthy",
    "positions": [
      "WR"
    ],
    "team": "KC",
    "age": 23.1,
    "headshot": "https://static.www.nfl.com/image/upload/f_auto,q_auto/league/ue6fp8xwnyo7ftvabbb8"
  },
  {
    "player_id": "00-0039384",
    "player_name": "Tyrone Tracy Jr.",
    "positions": [
      "RB"
    ],
    "team": "NYG",
    "age": 26.5,
    "headshot": "https://static.www.nfl.com/image/upload/f_auto,q_auto/league/b9nje50lohbprf06xoom"
  },
  {
    "player_id": "00-0038997",
    "player_name": "Josh Downs",
    "positions": [
      "WR"
    ],
    "team": "IND",
    "age": 24.8,
    "headshot": "https://static.www.nfl.com/image/upload/f_auto,q_auto/league/gqozitn9vxnp8acz6wwg"
  },
  {
    "player_id": "00-0034753",
    "player_name": "Mark Andrews",
    "positions": [
      "TE"
    ],
    "team": "BAL",
    "age": 30.7,
    "headshot": "https://static.www.nfl.com/image/upload/f_auto,q_auto/league/wzx3p0hzm3qyqsrfqznb"
  },
  {
    "player_id": "CON046719",
    "player_name": "KC Concepcion",
    "positions": [
      "WR"
    ],
    "team": "CLE",
    "age": 21.6,
    "headshot": null
  },
  {
    "player_id": "00-0037838",
    "player_name": "Isaiah Likely",
    "positions": [
      "TE"
    ],
    "team": "NYG",
    "age": 26.1,
    "headshot": "https://static.www.nfl.com/image/upload/f_auto,q_auto/league/ssrjtyvnyfflobmi0mb8"
  },
  {
    "player_id": "00-0037261",
    "player_name": "Khalil Shakir",
    "positions": [
      "WR"
    ],
    "team": "BUF",
    "age": 26.3,
    "headshot": "https://static.www.nfl.com/image/upload/f_auto,q_auto/league/otadttbhvkmavhsonnqm"
  },
  {
    "player_id": "00-0039163",
    "player_name": "C.J. Stroud",
    "positions": [
      "QB"
    ],
    "team": "HOU",
    "age": 24.6,
    "headshot": "https://static.www.nfl.com/image/upload/f_auto,q_auto/league/tt4zrtxlhifaljhj0rn7"
  },
  {
    "player_id": "00-0033090",
    "player_name": "Hunter Henry",
    "positions": [
      "TE"
    ],
    "team": "NE",
    "age": 31.4,
    "headshot": "https://static.www.nfl.com/image/upload/f_auto,q_auto/league/l0fsrutz9fwbohx10lcf"
  },
  {
    "player_id": "00-0034869",
    "player_name": "Sam Darnold",
    "positions": [
      "QB"
    ],
    "team": "SEA",
    "age": 29.0,
    "headshot": "https://static.www.nfl.com/image/upload/f_auto,q_auto/league/s5t8m6bhedjwwtfw3ild"
  },
  {
    "player_id": "00-0039344",
    "player_name": "Jonathon Brooks",
    "positions": [
      "RB"
    ],
    "team": "CAR",
    "age": 22.8,
    "headshot": "https://static.www.nfl.com/image/upload/f_auto,q_auto/league/jah18lvdpgwurx7dgys4"
  },
  {
    "player_id": "COL293648",
    "player_name": "Jonah Coleman",
    "positions": [
      "RB"
    ],
    "team": "DEN",
    "age": 22.7,
    "headshot": null
  },
  {
    "player_id": "00-0039491",
    "player_name": "Jalen Coker",
    "positions": [
      "WR"
    ],
    "team": "CAR",
    "age": 24.6,
    "headshot": "https://static.www.nfl.com/image/upload/f_auto,q_auto/league/tbo339znpzrfki8hri95"
  },
  {
    "player_id": "00-0038935",
    "player_name": "Brenton Strange",
    "positions": [
      "TE"
    ],
    "team": "JAX",
    "age": 25.4,
    "headshot": "https://static.www.nfl.com/image/upload/f_auto,q_auto/league/yabpcvadjlrkxzducv7k"
  },
  {
    "player_id": "00-0037197",
    "player_name": "Isiah Pacheco",
    "positions": [
      "RB"
    ],
    "team": "DET",
    "age": 27.2,
    "headshot": "https://static.www.nfl.com/image/upload/f_auto,q_auto/league/tqshteijt4xhgk2ei9sx"
  },
  {
    "player_id": "00-0036040",
    "player_name": "Juwan Johnson",
    "positions": [
      "TE"
    ],
    "team": "NO",
    "age": 29.7,
    "headshot": "https://static.www.nfl.com/image/upload/f_auto,q_auto/league/wuyyzdqkh5fve8t7kfuv"
  },
  {
    "player_id": "00-0039794",
    "player_name": "Braelon Allen",
    "positions": [
      "RB"
    ],
    "team": "NYJ",
    "age": 22.3,
    "headshot": "https://static.www.nfl.com/image/upload/f_auto,q_auto/league/pdaa8u0x2qepyklabdr3"
  },
  {
    "player_id": "00-0040667",
    "player_name": "Matthew Golden",
    "positions": [
      "WR"
    ],
    "team": "GB",
    "age": 22.8,
    "headshot": "https://static.www.nfl.com/image/upload/f_auto,q_auto/league/gkbhlytvkltv5whjo3ru"
  },
  {
    "player_id": "00-0037545",
    "player_name": "Rashid Shaheed",
    "positions": [
      "WR"
    ],
    "team": "SEA",
    "age": 27.7,
    "headshot": "https://static.www.nfl.com/image/upload/f_auto,q_auto/league/ynsy489xqmiwt5q9whty"
  },
  {
    "player_id": "BOS677861",
    "player_name": "Denzel Boston",
    "positions": [
      "WR"
    ],
    "team": "CLE",
    "age": 22.5,
    "headshot": null
  },
  {
    "player_id": "00-0040162",
    "player_name": "Dylan Sampson",
    "positions": [
      "RB"
    ],
    "team": "CLE",
    "age": 21.7,
    "headshot": "https://static.www.nfl.com/image/upload/f_auto,q_auto/league/den1hzzomdxfcsgk88o5"
  },
  {
    "player_id": "00-0033553",
    "player_name": "James Conner",
    "positions": [
      "RB"
    ],
    "team": "ARI",
    "age": 31.0,
    "headshot": "https://static.www.nfl.com/image/upload/f_auto,q_auto/league/g5yjordcmt76j0saytzb"
  },
  {
    "player_id": "00-0033906",
    "player_name": "Alvin Kamara",
    "positions": [
      "RB"
    ],
    "team": "NO",
    "age": 30.8,
    "headshot": "https://static.www.nfl.com/image/upload/f_auto,q_auto/league/uay6uo9lonegelngihki"
  },
  {
    "player_id": "00-0038555",
    "player_name": "Tank Bigsby",
    "positions": [
      "RB"
    ],
    "team": "PHI",
    "age": 23.7,
    "headshot": "https://static.www.nfl.com/image/upload/f_auto,q_auto/league/nin8aexyipca7g7u7f4a"
  },
  {
    "player_id": "00-0039150",
    "player_name": "Bryce Young",
    "positions": [
      "QB"
    ],
    "team": "CAR",
    "age": 24.8,
    "headshot": "https://static.www.nfl.com/image/upload/f_auto,q_auto/league/qy1lfhlzhiacsyzzm1j7"
  },
  {
    "player_id": "00-0039032",
    "player_name": "Tyjae Spears",
    "positions": [
      "RB"
    ],
    "team": "TEN",
    "age": 24.9,
    "headshot": "https://static.www.nfl.com/image/upload/f_auto,q_auto/league/fc7vhbtw80einad9hsfu"
  },
  {
    "player_id": "00-0037746",
    "player_name": "Brian Robinson Jr.",
    "positions": [
      "RB"
    ],
    "team": "ATL",
    "age": 27.2,
    "headshot": "https://static.www.nfl.com/image/upload/f_auto,q_auto/league/n1xhex1ytisxcbcggqu7"
  },
  {
    "player_id": "00-0038454",
    "player_name": "Keaton Mitchell",
    "positions": [
      "RB"
    ],
    "team": "LAC",
    "age": 24.3,
    "headshot": "https://static.www.nfl.com/image/upload/f_auto,q_auto/league/klpn2btfhgfv5a8dp3jj"
  },
  {
    "player_id": "COO816508",
    "player_name": "Omar Cooper Jr.",
    "positions": [
      "WR"
    ],
    "team": "NYJ",
    "age": 22.4,
    "headshot": null
  },
  {
    "player_id": "00-0040676",
    "player_name": "Cam Ward",
    "positions": [
      "QB"
    ],
    "team": "TEN",
    "age": 24.0,
    "headshot": "https://static.www.nfl.com/image/upload/f_auto,q_auto/league/viadutkbvligsopnd2qn"
  },
  {
    "player_id": "00-0038797",
    "player_name": "Emanuel Wilson",
    "positions": [
      "RB"
    ],
    "team": "SEA",
    "age": 27.0,
    "headshot": "https://static.www.nfl.com/image/upload/f_auto,q_auto/league/xni9gnwmhdex7h1ey3jq"
  },
  {
    "player_id": "SAD482340",
    "player_name": "Kenyon Sadiq",
    "positions": [
      "TE"
    ],
    "team": "NYJ",
    "age": 21.2,
    "headshot": null
  },
  {
    "player_id": "00-0036261",
    "player_name": "Brandon Aiyuk",
    "positions": [
      "WR"
    ],
    "team": "SF",
    "age": 28.2,
    "headshot": "https://static.www.nfl.com/image/upload/f_auto,q_auto/league/avzzxycxyculxxqce5k7"
  },
  {
    "player_id": "WAS569019",
    "player_name": "Mike Washington Jr.",
    "positions": [
      "RB"
    ],
    "team": "LV",
    "age": 72.9,
    "headshot": "https://static.www.nfl.com/image/private/f_auto,q_auto/league/mv0tazy4ajfudzgcklqr"
  },
  {
    "player_id": "00-0036259",
    "player_name": "Jauan Jennings",
    "positions": [
      "WR"
    ],
    "team": "MIN",
    "age": 28.9,
    "headshot": "https://static.www.nfl.com/image/upload/f_auto,q_auto/league/cdx9mq3iglzog9mkqvdr"
  },
  {
    "player_id": "JOH224817",
    "player_name": "Emmett Johnson",
    "positions": [
      "RB"
    ],
    "team": "KC",
    "age": 22.6,
    "headshot": null
  },
  {
    "player_id": "00-0036407",
    "player_name": "Jerry Jeudy",
    "positions": [
      "WR"
    ],
    "team": "CLE",
    "age": 27.1,
    "headshot": "https://static.www.nfl.com/image/upload/f_auto,q_auto/league/szca1v9butuqkjs7ekpm"
  },
  {
    "player_id": "00-0035710",
    "player_name": "Daniel Jones",
    "positions": [
      "QB"
    ],
    "team": "IND",
    "age": 29.0,
    "headshot": "https://static.www.nfl.com/image/upload/f_auto,q_auto/league/nhuiypfjzpkisxllinyv"
  },
  {
    "player_id": "00-0039890",
    "player_name": "Adonai Mitchell",
    "positions": [
      "WR"
    ],
    "team": "NYJ",
    "age": 23.6,
    "headshot": "https://static.www.nfl.com/image/upload/f_auto,q_auto/league/hwwacoa3pqapd7pgahfx"
  },
  {
    "player_id": "00-0038608",
    "player_name": "Kayshon Boutte",
    "positions": [
      "WR"
    ],
    "team": "NE",
    "age": 24.0,
    "headshot": "https://static.www.nfl.com/image/upload/f_auto,q_auto/league/mg4icjqhwhnc5uobmau5"
  },
  {
    "player_id": "SIN454221",
    "player_name": "Nicholas Singleton",
    "positions": [
      "RB"
    ],
    "team": "TEN",
    "age": 22.4,
    "headshot": null
  },
  {
    "player_id": "00-0040718",
    "player_name": "Travis Hunter",
    "positions": [
      "WR"
    ],
    "team": "JAX",
    "age": 23.0,
    "headshot": "https://static.www.nfl.com/image/upload/f_auto,q_auto/league/apfzii6u8pwj9ntvyfkk"
  },
  {
    "player_id": "00-0031588",
    "player_name": "Stefon Diggs",
    "positions": [
      "WR"
    ],
    "team": "FA",
    "age": 32.5,
    "headshot": "https://static.www.nfl.com/image/upload/f_auto,q_auto/league/cemcexmscsarpvwhafln"
  },
  {
    "player_id": "00-0035719",
    "player_name": "Deebo Samuel Sr.",
    "positions": [
      "WR"
    ],
    "team": "FA",
    "age": 30.3,
    "headshot": "https://static.www.nfl.com/image/upload/f_auto,q_auto/league/ntgyhqg6hq7fanhhsqiw"
  },
  {
    "player_id": "WIL143106",
    "player_name": "Antonio Williams",
    "positions": [
      "WR"
    ],
    "team": "WAS",
    "age": 21.8,
    "headshot": null
  },
  {
    "player_id": "ALL532376",
    "player_name": "Kaytron Allen",
    "positions": [
      "RB"
    ],
    "team": "WAS",
    "age": 23.4,
    "headshot": null
  },
  {
    "player_id": "00-0039391",
    "player_name": "Kimani Vidal",
    "positions": [
      "RB"
    ],
    "team": "LAC",
    "age": 24.7,
    "headshot": "https://static.www.nfl.com/image/upload/f_auto,q_auto/league/huwihtava8gkxzb4cxb8"
  },
  {
    "player_id": "00-0034383",
    "player_name": "Dalton Schultz",
    "positions": [
      "TE"
    ],
    "team": "HOU",
    "age": 29.9,
    "headshot": "https://static.www.nfl.com/image/upload/f_auto,q_auto/league/xbl9mhuamzv5udb4hyzj"
  },
  {
    "player_id": "00-0039855",
    "player_name": "Jalen McMillan",
    "positions": [
      "WR"
    ],
    "team": "TB",
    "age": 24.4,
    "headshot": "https://static.www.nfl.com/image/upload/f_auto,q_auto/league/x2jipyhqclsgx4cmsqct"
  },
  {
    "player_id": "00-0037809",
    "player_name": "Chig Okonkwo",
    "positions": [
      "TE"
    ],
    "team": "WAS",
    "age": 26.7,
    "headshot": "https://static.www.nfl.com/image/upload/f_auto,q_auto/league/omm5z5iq6dlmidqz1sgz"
  },
  {
    "player_id": "00-0040737",
    "player_name": "Terrance Ferguson",
    "positions": [
      "TE"
    ],
    "team": "LA",
    "age": 23.2,
    "headshot": "https://static.www.nfl.com/image/upload/f_auto,q_auto/league/usa23ax8dratptvikr9a"
  },
  {
    "player_id": "00-0039874",
    "player_name": "Jaylen Wright",
    "positions": [
      "RB"
    ],
    "team": "MIA",
    "age": 23.1,
    "headshot": "https://static.www.nfl.com/image/upload/f_auto,q_auto/league/i3wlfgqsynl7qaa4tsqw"
  },
  {
    "player_id": "00-0039875",
    "player_name": "Ray Davis",
    "positions": [
      "RB"
    ],
    "team": "BUF",
    "age": 26.5,
    "headshot": "https://static.www.nfl.com/image/upload/f_auto,q_auto/league/pm9llppbueodtjjj9u8l"
  },
  {
    "player_id": "00-0039868",
    "player_name": "Troy Franklin",
    "positions": [
      "WR"
    ],
    "team": "DEN",
    "age": 23.3,
    "headshot": "https://static.www.nfl.com/image/upload/f_auto,q_auto/league/belpdlyoda8cmzbvjkqh"
  },
  {
    "player_id": "00-0039793",
    "player_name": "AJ Barner",
    "positions": [
      "TE"
    ],
    "team": "SEA",
    "age": 24.0,
    "headshot": "https://static.www.nfl.com/image/upload/f_auto,q_auto/league/ul77k5rqbqzd5zzqsaea"
  },
  {
    "player_id": "00-0033040",
    "player_name": "Tyreek Hill",
    "positions": [
      "WR"
    ],
    "team": "FA",
    "age": 32.2,
    "headshot": "https://static.www.nfl.com/image/upload/f_auto,q_auto/league/gg73gnfivrn80oyqwazl"
  },
  {
    "player_id": "00-0033119",
    "player_name": "Jacoby Brissett",
    "positions": [
      "QB"
    ],
    "team": "ARI",
    "age": 33.4,
    "headshot": "https://static.www.nfl.com/image/upload/f_auto,q_auto/league/rdxowm5dvpbb8p3aazbc"
  },
  {
    "player_id": "00-0040669",
    "player_name": "Isaac TeSlaa",
    "positions": [
      "WR"
    ],
    "team": "DET",
    "age": 24.2,
    "headshot": "https://static.www.nfl.com/image/upload/f_auto,q_auto/league/wa4sruqazyqobmepi6vi"
  },
  {
    "player_id": "00-0038951",
    "player_name": "Sean Tucker",
    "positions": [
      "RB"
    ],
    "team": "TB",
    "age": 24.6,
    "headshot": "https://static.www.nfl.com/image/upload/f_auto,q_auto/league/zyzp7e2gos47ebzur9gi"
  },
  {
    "player_id": "00-0038563",
    "player_name": "Tre Tucker",
    "positions": [
      "WR"
    ],
    "team": "LV",
    "age": 25.2,
    "headshot": "https://static.www.nfl.com/image/upload/f_auto,q_auto/league/fsx05ats4azj8mus03d4"
  },
  {
    "player_id": "00-0040727",
    "player_name": "Tre' Harris",
    "positions": [
      "WR"
    ],
    "team": "LAC",
    "age": 24.2,
    "headshot": "https://static.www.nfl.com/image/upload/f_auto,q_auto/league/vfjekjvrfpbmskmuwoz9"
  },
  {
    "player_id": "00-0034837",
    "player_name": "Calvin Ridley",
    "positions": [
      "WR"
    ],
    "team": "TEN",
    "age": 31.4,
    "headshot": "https://static.www.nfl.com/image/upload/f_auto,q_auto/league/l96rlegwqz7qfakbdtlp"
  },
  {
    "player_id": "00-0035229",
    "player_name": "T.J. Hockenson",
    "positions": [
      "TE"
    ],
    "team": "MIN",
    "age": 28.9,
    "headshot": "https://static.www.nfl.com/image/upload/f_auto,q_auto/league/rs8o65x0u0n9xzde0fd6"
  },
  {
    "player_id": "CLA041524",
    "player_name": "Demond Claiborne",
    "positions": [
      "RB"
    ],
    "team": "MIN",
    "age": 22.6,
    "headshot": null
  },
  {
    "player_id": "00-0040138",
    "player_name": "Jaylin Noel",
    "positions": [
      "WR"
    ],
    "team": "HOU",
    "age": 23.7,
    "headshot": "https://static.www.nfl.com/image/upload/f_auto,q_auto/league/dajbyvtsggwqinlijxnf"
  },
  {
    "player_id": "STO806346",
    "player_name": "Eli Stowers",
    "positions": [
      "TE"
    ],
    "team": "PHI",
    "age": 23.1,
    "headshot": null
  },
  {
    "player_id": "BER218265",
    "player_name": "Germie Bernard",
    "positions": [
      "WR"
    ],
    "team": "PIT",
    "age": 22.5,
    "headshot": null
  },
  {
    "player_id": "00-0040705",
    "player_name": "Chimere Dike",
    "positions": [
      "WR"
    ],
    "team": "TEN",
    "age": 24.4,
    "headshot": "https://static.www.nfl.com/image/upload/f_auto,q_auto/league/njdduv9jx7c8vlrll8ex"
  },
  {
    "player_id": "00-0036309",
    "player_name": "Darnell Mooney",
    "positions": [
      "WR"
    ],
    "team": "NYG",
    "age": 28.6,
    "headshot": "https://static.www.nfl.com/image/upload/f_auto,q_auto/league/eaejonwaflt9drrs9ika"
  },
  {
    "player_id": "00-0038977",
    "player_name": "Tank Dell",
    "positions": [
      "WR"
    ],
    "team": "HOU",
    "age": 26.6,
    "headshot": "https://static.www.nfl.com/image/upload/f_auto,q_auto/league/ykyiamjbjkjklnnttisw"
  },
  {
    "player_id": "00-0039410",
    "player_name": "Ryan Flournoy",
    "positions": [
      "WR"
    ],
    "team": "DAL",
    "age": 26.6,
    "headshot": "https://static.www.nfl.com/image/upload/f_auto,q_auto/league/tqwq3cgpqu7j9hzoyicx"
  },
  {
    "player_id": "00-0040198",
    "player_name": "Ollie Gordon II",
    "positions": [
      "RB"
    ],
    "team": "MIA",
    "age": 22.3,
    "headshot": "https://static.www.nfl.com/image/upload/f_auto,q_auto/league/bv33rgypaauv7sealwkr"
  },
  {
    "player_id": "00-0040134",
    "player_name": "Pat Bryant",
    "positions": [
      "WR"
    ],
    "team": "DEN",
    "age": 23.4,
    "headshot": "https://static.www.nfl.com/image/upload/f_auto,q_auto/league/ljo1rgbaewlzsf7tvavm"
  },
  {
    "player_id": "BEL267684",
    "player_name": "Chris Bell",
    "positions": [
      "WR"
    ],
    "team": "MIA",
    "age": 21.9,
    "headshot": null
  },
  {
    "player_id": "00-0040170",
    "player_name": "Elic Ayomanor",
    "positions": [
      "WR"
    ],
    "team": "TEN",
    "age": 23.0,
    "headshot": "https://static.www.nfl.com/image/upload/f_auto,q_auto/league/aekfvt5nyl69emvxr2yj"
  },
  {
    "player_id": "SAR527100",
    "player_name": "Elijah Sarratt",
    "positions": [
      "WR"
    ],
    "team": "BAL",
    "age": 23.0,
    "headshot": null
  },
  {
    "player_id": "STR336088",
    "player_name": "De'Zhaun Stribling",
    "positions": [
      "WR"
    ],
    "team": "SF",
    "age": 23.4,
    "headshot": null
  },
  {
    "player_id": "LAN311008",
    "player_name": "Ja'Kobi Lane",
    "positions": [
      "WR"
    ],
    "team": "BAL",
    "age": 21.8,
    "headshot": null
  },
  {
    "player_id": "00-0033885",
    "player_name": "David Njoku",
    "positions": [
      "TE"
    ],
    "team": "LAC",
    "age": 29.9,
    "headshot": "https://static.www.nfl.com/image/upload/f_auto,q_auto/league/gdwtgcfz3mxj6codxdpn"
  },
  {
    "player_id": "BRA531428",
    "player_name": "Zachariah Branch",
    "positions": [
      "WR"
    ],
    "team": "ATL",
    "age": 22.1,
    "headshot": null
  },
  {
    "player_id": "RAN022436",
    "player_name": "Adam Randall",
    "positions": [
      "RB"
    ],
    "team": "BAL",
    "age": 21.8,
    "headshot": null
  },
  {
    "player_id": "00-0038551",
    "player_name": "Kendre Miller",
    "positions": [
      "RB"
    ],
    "team": "NO",
    "age": 23.9,
    "headshot": "https://static.www.nfl.com/image/upload/f_auto,q_auto/league/jz3mpvifmldus3ipdvu1"
  },
  {
    "player_id": "00-0038393",
    "player_name": "Dontayvion Wicks",
    "positions": [
      "WR"
    ],
    "team": "PHI",
    "age": 24.9,
    "headshot": "https://static.www.nfl.com/image/upload/f_auto,q_auto/league/er7pbyq82nsbw1w3wyor"
  },
  {
    "player_id": "MEN516487",
    "player_name": "Fernando Mendoza",
    "positions": [
      "QB"
    ],
    "team": "LV",
    "age": 22.6,
    "headshot": null
  },
  {
    "player_id": "00-0040202",
    "player_name": "Devin Neal",
    "positions": [
      "RB"
    ],
    "team": "NO",
    "age": 22.8,
    "headshot": "https://static.www.nfl.com/image/upload/f_auto,q_auto/league/e0pzghslevb27ssozx4s"
  },
  {
    "player_id": "00-0040131",
    "player_name": "Kyle Williams",
    "positions": [
      "WR"
    ],
    "team": "NE",
    "age": 23.5,
    "headshot": "https://static.www.nfl.com/image/upload/f_auto,q_auto/league/bu31c2ino065kazsn541"
  },
  {
    "player_id": "00-0040584",
    "player_name": "Gunnar Helm",
    "positions": [
      "TE"
    ],
    "team": "TEN",
    "age": 23.7,
    "headshot": "https://static.www.nfl.com/image/upload/f_auto,q_auto/league/lcyqbbnrzgtbnirz8knj"
  },
  {
    "player_id": "00-0037291",
    "player_name": "Jalen Nailor",
    "positions": [
      "WR"
    ],
    "team": "LV",
    "age": 27.2,
    "headshot": "https://static.www.nfl.com/image/upload/f_auto,q_auto/league/sdsx2pttiiwbfpyuuwiz"
  },
  {
    "player_id": "BRA836631",
    "player_name": "Chris Brazzell II",
    "positions": [
      "WR"
    ],
    "team": "CAR",
    "age": 22.6,
    "headshot": null
  },
  {
    "player_id": "00-0040142",
    "player_name": "Kaleb Johnson",
    "positions": [
      "RB"
    ],
    "team": "PIT",
    "age": 22.8,
    "headshot": "https://static.www.nfl.com/image/upload/f_auto,q_auto/league/sblojderaku4qta1lj2b"
  },
  {
    "player_id": "00-0036550",
    "player_name": "Rashod Bateman",
    "positions": [
      "WR"
    ],
    "team": "BAL",
    "age": 26.5,
    "headshot": "https://static.www.nfl.com/image/upload/f_auto,q_auto/league/gtktmsfcxc1eijwpwzyq"
  },
  {
    "player_id": "00-0039847",
    "player_name": "Theo Johnson",
    "positions": [
      "TE"
    ],
    "team": "NYG",
    "age": 25.2,
    "headshot": "https://static.www.nfl.com/image/upload/f_auto,q_auto/league/naoiheinxogchairenzf"
  },
  {
    "player_id": "00-0036244",
    "player_name": "Colby Parkinson",
    "positions": [
      "TE"
    ],
    "team": "LA",
    "age": 27.4,
    "headshot": "https://static.www.nfl.com/image/upload/f_auto,q_auto/league/b1qzivnz0zqa8cjgah8r"
  },
  {
    "player_id": "00-0036894",
    "player_name": "Pat Freiermuth",
    "positions": [
      "TE"
    ],
    "team": "PIT",
    "age": 27.6,
    "headshot": "https://static.www.nfl.com/image/upload/f_auto,q_auto/league/vmwioi77upc9hqwaskfa"
  },
  {
    "player_id": "00-0039921",
    "player_name": "Trey Benson",
    "positions": [
      "RB"
    ],
    "team": "ARI",
    "age": 23.8,
    "headshot": "https://static.www.nfl.com/image/upload/f_auto,q_auto/league/x2bxb0fd54ffwwdu5scz"
  },
  {
    "player_id": "FIE775129",
    "player_name": "Malachi Fields",
    "positions": [
      "WR"
    ],
    "team": "NYG",
    "age": 23.9,
    "headshot": null
  },
  {
    "player_id": "BEL597603",
    "player_name": "Skyler Bell",
    "positions": [
      "WR"
    ],
    "team": "BUF",
    "age": 23.9,
    "headshot": null
  },
  {
    "player_id": "00-0030565",
    "player_name": "Geno Smith",
    "positions": [
      "QB"
    ],
    "team": "NYJ",
    "age": 35.6,
    "headshot": "https://static.www.nfl.com/image/upload/f_auto,q_auto/league/tqy0933vz5yogwlefb1s"
  },
  {
    "player_id": "00-0040648",
    "player_name": "Tory Horton",
    "positions": [
      "WR"
    ],
    "team": "SEA",
    "age": 23.5,
    "headshot": "https://static.www.nfl.com/image/upload/f_auto,q_auto/league/vpgs86vlcp3gejw6tget"
  },
  {
    "player_id": "00-0038129",
    "player_name": "Cade Otton",
    "positions": [
      "TE"
    ],
    "team": "TB",
    "age": 27.1,
    "headshot": "https://static.www.nfl.com/image/upload/f_auto,q_auto/league/dlgxvfpnufpnxkvu1ynb"
  },
  {
    "player_id": "00-0039917",
    "player_name": "Michael Penix Jr.",
    "positions": [
      "QB"
    ],
    "team": "ATL",
    "age": 26.0,
    "headshot": "https://static.www.nfl.com/image/upload/f_auto,q_auto/league/azvyjzp2sa8cnljbp3i7"
  },
  {
    "player_id": "00-0036893",
    "player_name": "Najee Harris",
    "positions": [
      "RB"
    ],
    "team": "LAC",
    "age": 28.2,
    "headshot": "https://static.www.nfl.com/image/upload/f_auto,q_auto/league/grfxgbvqnzz40r7rdtvk"
  },
  {
    "player_id": "HUR541377",
    "player_name": "Ted Hurst",
    "positions": [
      "WR"
    ],
    "team": "TB",
    "age": 21.9,
    "headshot": null
  },
  {
    "player_id": "00-0040736",
    "player_name": "Mason Taylor",
    "positions": [
      "TE"
    ],
    "team": "NYJ",
    "age": 22.0,
    "headshot": "https://static.www.nfl.com/image/upload/f_auto,q_auto/league/bk7wjtjt7dpc5qsuil4z"
  },
  {
    "player_id": "00-0039901",
    "player_name": "Keon Coleman",
    "positions": [
      "WR"
    ],
    "team": "BUF",
    "age": 23.0,
    "headshot": "https://static.www.nfl.com/image/upload/f_auto,q_auto/league/f3cx4kmpdmqftr79ueiv"
  },
  {
    "player_id": "00-0039798",
    "player_name": "Isaiah Davis",
    "positions": [
      "RB"
    ],
    "team": "NYJ",
    "age": 24.2,
    "headshot": "https://static.www.nfl.com/image/upload/f_auto,q_auto/league/hsozhwgsuffsfrc4qdp2"
  },
  {
    "player_id": "00-0040586",
    "player_name": "Jaydon Blue",
    "positions": [
      "RB"
    ],
    "team": "DAL",
    "age": 22.4,
    "headshot": "https://static.www.nfl.com/image/upload/f_auto,q_auto/league/jhbmit7yp8dlhepncsvp"
  },
  {
    "player_id": "00-0038976",
    "player_name": "Marvin Mims Jr.",
    "positions": [
      "WR"
    ],
    "team": "DEN",
    "age": 24.2,
    "headshot": "https://static.www.nfl.com/image/upload/f_auto,q_auto/league/zbdjtph5xplbf4yocz0l"
  },
  {
    "player_id": "00-0033881",
    "player_name": "Evan Engram",
    "positions": [
      "TE"
    ],
    "team": "DEN",
    "age": 31.7,
    "headshot": "https://static.www.nfl.com/image/upload/f_auto,q_auto/league/vsrjso6phkjqki88qw9y"
  },
  {
    "player_id": "00-0039880",
    "player_name": "Malik Washington",
    "positions": [
      "WR"
    ],
    "team": "MIA",
    "age": 25.6,
    "headshot": "https://static.www.nfl.com/image/upload/f_auto,q_auto/league/kwcgtsbpd0rpwsgq2npe"
  },
  {
    "player_id": "00-0035537",
    "player_name": "Ty Johnson",
    "positions": [
      "RB"
    ],
    "team": "BUF",
    "age": 28.7,
    "headshot": "https://static.www.nfl.com/image/upload/f_auto,q_auto/league/hmnzcfm56ojey6myomjg"
  },
  {
    "player_id": "00-0033908",
    "player_name": "Cooper Kupp",
    "positions": [
      "WR"
    ],
    "team": "SEA",
    "age": 32.9,
    "headshot": "https://static.www.nfl.com/image/upload/f_auto,q_auto/league/lpaxi9rsedlg9sdr5quw"
  },
  {
    "player_id": "00-0023459",
    "player_name": "Aaron Rodgers",
    "positions": [
      "QB"
    ],
    "team": "PIT",
    "age": 42.5,
    "headshot": "https://static.www.nfl.com/image/upload/f_auto,q_auto/league/dypvakakxhccxs67tb0y"
  },
  {
    "player_id": "00-0040668",
    "player_name": "Shedeur Sanders",
    "positions": [
      "QB"
    ],
    "team": "CLE",
    "age": 24.3,
    "headshot": "https://static.www.nfl.com/image/upload/f_auto,q_auto/league/joe08hz6to2madpko8zl"
  },
  {
    "player_id": "00-0035250",
    "player_name": "Devin Singletary",
    "positions": [
      "RB"
    ],
    "team": "NYG",
    "age": 28.7,
    "headshot": "https://static.www.nfl.com/image/upload/f_auto,q_auto/league/wqw8ee4nsxsisqb3bagw"
  },
  {
    "player_id": "00-0040177",
    "player_name": "Jordan James",
    "positions": [
      "RB"
    ],
    "team": "SF",
    "age": 22.1,
    "headshot": "https://static.www.nfl.com/image/upload/f_auto,q_auto/league/vhkfigionbm4xwjcbfzg"
  },
  {
    "player_id": "00-0034775",
    "player_name": "Christian Kirk",
    "positions": [
      "WR"
    ],
    "team": "SF",
    "age": 29.5,
    "headshot": "https://static.www.nfl.com/image/upload/f_auto,q_auto/league/bugikrmfz5k4jvyaogza"
  },
  {
    "player_id": "00-0040078",
    "player_name": "Brashard Smith",
    "positions": [
      "RB"
    ],
    "team": "KC",
    "age": 23.1,
    "headshot": "https://static.www.nfl.com/image/upload/f_auto,q_auto/league/u3t4csj7hhcgymvb8ldf"
  },
  {
    "player_id": "00-0040179",
    "player_name": "DJ Giddens",
    "positions": [
      "RB"
    ],
    "team": "IND",
    "age": 22.7,
    "headshot": "https://static.www.nfl.com/image/upload/f_auto,q_auto/league/uohb3wkn00ew1chqyjue"
  },
  {
    "player_id": "KLA269938",
    "player_name": "Max Klare",
    "positions": [
      "TE"
    ],
    "team": "LA",
    "age": 22.9,
    "headshot": null
  },
  {
    "player_id": "00-0033555",
    "player_name": "Mack Hollins",
    "positions": [
      "WR"
    ],
    "team": "NE",
    "age": 32.7,
    "headshot": "https://static.www.nfl.com/image/upload/f_auto,q_auto/league/qbz7whjzsittudcecezw"
  },
  {
    "player_id": "00-0035535",
    "player_name": "Darius Slayton",
    "positions": [
      "WR"
    ],
    "team": "NYG",
    "age": 29.3,
    "headshot": "https://static.www.nfl.com/image/upload/f_auto,q_auto/league/fyjkvaekv40jn72d0b3q"
  },
  {
    "player_id": "00-0030279",
    "player_name": "Keenan Allen",
    "positions": [
      "WR"
    ],
    "team": "LAC",
    "age": 34.1,
    "headshot": "https://static.www.nfl.com/image/upload/f_auto,q_auto/league/ri267r6lzfwarh89hsn6"
  },
  {
    "player_id": "00-0037112",
    "player_name": "Jake Tonges",
    "positions": [
      "TE"
    ],
    "team": "SF",
    "age": 26.9,
    "headshot": "https://static.www.nfl.com/image/upload/f_auto,q_auto/league/uztcdowl4wig2uhy1qxh"
  },
  {
    "player_id": "00-0040729",
    "player_name": "Jack Bech",
    "positions": [
      "WR"
    ],
    "team": "LV",
    "age": 23.4,
    "headshot": "https://static.www.nfl.com/image/upload/f_auto,q_auto/league/feplgtl0x1svqen9szwv"
  },
  {
    "player_id": "00-0039363",
    "player_name": "Isaac Guerendo",
    "positions": [
      "RB"
    ],
    "team": "SF",
    "age": 25.9,
    "headshot": "https://static.www.nfl.com/image/upload/f_auto,q_auto/league/lr1qp5tsa5xshzt02urm"
  },
  {
    "player_id": "00-0037563",
    "player_name": "Malik Davis",
    "positions": [
      "RB"
    ],
    "team": "DAL",
    "age": 27.5,
    "headshot": "https://static.www.nfl.com/image/upload/f_auto,q_auto/league/mdjhv8xuitxkn7oefwty"
  },
  {
    "player_id": "00-0039342",
    "player_name": "Xavier Legette",
    "positions": [
      "WR"
    ],
    "team": "CAR",
    "age": 25.3,
    "headshot": "https://static.www.nfl.com/image/upload/f_auto,q_auto/league/j4jj8rvgzji7zut86ux7"
  },
  {
    "player_id": "00-0039811",
    "player_name": "MarShawn Lloyd",
    "positions": [
      "RB"
    ],
    "team": "GB",
    "age": 25.4,
    "headshot": "https://static.www.nfl.com/image/upload/f_auto,q_auto/league/ufhthbjqbgb6mggscdc9"
  },
  {
    "player_id": "00-0034975",
    "player_name": "Justice Hill",
    "positions": [
      "RB"
    ],
    "team": "BAL",
    "age": 28.5,
    "headshot": "https://static.www.nfl.com/image/upload/f_auto,q_auto/league/h6p9crhra8ehxju3ubza"
  },
  {
    "player_id": "00-0033897",
    "player_name": "Joe Mixon",
    "positions": [
      "RB"
    ],
    "team": "FA",
    "age": 29.8,
    "headshot": "https://static.www.nfl.com/image/upload/f_auto,q_auto/league/gwyhozfhjgedwdmmjjcf"
  },
  {
    "player_id": "00-0038685",
    "player_name": "Chris Brooks",
    "positions": [
      "RB"
    ],
    "team": "GB",
    "age": 26.4,
    "headshot": "https://static.www.nfl.com/image/upload/f_auto,q_auto/league/nnwloijqopel4em6vfhb"
  },
  {
    "player_id": "00-0034829",
    "player_name": "Mike Gesicki",
    "positions": [
      "TE"
    ],
    "team": "CIN",
    "age": 30.6,
    "headshot": "https://static.www.nfl.com/image/upload/f_auto,q_auto/league/mfswo0trev4oi2gnb41e"
  },
  {
    "player_id": "00-0039299",
    "player_name": "George Holani",
    "positions": [
      "RB"
    ],
    "team": "SEA",
    "age": 26.4,
    "headshot": "https://static.www.nfl.com/image/upload/f_auto,q_auto/league/nadkmkb2sqgjhbkpirkg"
  },
  {
    "player_id": "00-0038104",
    "player_name": "Tyquan Thornton",
    "positions": [
      "WR"
    ],
    "team": "KC",
    "age": 25.8,
    "headshot": "https://static.www.nfl.com/image/upload/f_auto,q_auto/league/bjqzuempyiwxe0hl7e5a"
  },
  {
    "player_id": "00-0036212",
    "player_name": "Tua Tagovailoa",
    "positions": [
      "QB"
    ],
    "team": "ATL",
    "age": 28.2,
    "headshot": "https://static.www.nfl.com/image/upload/f_auto,q_auto/league/ktqj3s5vofexl2dwrrp4"
  },
  {
    "player_id": "00-0039424",
    "player_name": "Devaughn Vele",
    "positions": [
      "WR"
    ],
    "team": "NO",
    "age": 28.4,
    "headshot": "https://static.www.nfl.com/image/upload/f_auto,q_auto/league/sxlrltvxbb2utwgjgdbt"
  },
  {
    "player_id": "00-0038705",
    "player_name": "Emari Demercado",
    "positions": [
      "RB"
    ],
    "team": "KC",
    "age": 27.3,
    "headshot": "https://static.www.nfl.com/image/upload/f_auto,q_auto/league/jasnk9akri8eghfgolsn"
  },
  {
    "player_id": "00-0033526",
    "player_name": "Samaje Perine",
    "positions": [
      "RB"
    ],
    "team": "CIN",
    "age": 30.7,
    "headshot": "https://static.www.nfl.com/image/upload/f_auto,q_auto/league/ur3jv6biq0pefkrgpzty"
  },
  {
    "player_id": "MCG547540",
    "player_name": "Seth McGowan",
    "positions": [
      "RB"
    ],
    "team": "IND",
    "age": 24.6,
    "headshot": null
  },
  {
    "player_id": "00-0037267",
    "player_name": "Jerome Ford",
    "positions": [
      "RB"
    ],
    "team": "WAS",
    "age": 26.7,
    "headshot": "https://static.www.nfl.com/image/private/f_auto,q_auto/league/djggmwo5v8osoboiseo2"
  },
  {
    "player_id": "00-0035662",
    "player_name": "Hollywood Brown",
    "positions": [
      "WR"
    ],
    "team": "PHI",
    "age": 29.0,
    "headshot": "https://static.www.nfl.com/image/upload/f_auto,q_auto/league/ixuddegcphzmvjn4jq6r"
  },
  {
    "player_id": "00-0033537",
    "player_name": "Deshaun Watson",
    "positions": [
      "QB"
    ],
    "team": "CLE",
    "age": 30.7,
    "headshot": "https://static.www.nfl.com/image/private/f_auto,q_auto/league/otfs2docj6eahaebo5xn"
  },
  {
    "player_id": "00-0040782",
    "player_name": "Isaiah Bond",
    "positions": [
      "WR"
    ],
    "team": "CLE",
    "age": 22.2,
    "headshot": "https://static.www.nfl.com/image/upload/f_auto,q_auto/league/piv889pkizjvgrtpfkxm"
  },
  {
    "player_id": "00-0040238",
    "player_name": "LeQuint Allen Jr.",
    "positions": [
      "RB"
    ],
    "team": "JAX",
    "age": 21.8,
    "headshot": "https://static.www.nfl.com/image/upload/f_auto,q_auto/league/i0utigksuuvo2njb9wtk"
  },
  {
    "player_id": "00-0029604",
    "player_name": "Kirk Cousins",
    "positions": [
      "QB"
    ],
    "team": "LV",
    "age": 37.7,
    "headshot": "https://static.www.nfl.com/image/upload/f_auto,q_auto/league/hmdqr7gju0dciapvdjcv"
  },
  {
    "player_id": "00-0038794",
    "player_name": "Jaleel McLaughlin",
    "positions": [
      "RB"
    ],
    "team": "DEN",
    "age": 25.7,
    "headshot": "https://static.www.nfl.com/image/upload/f_auto,q_auto/league/pw2tngyy8k8jlb1qpooo"
  },
  {
    "player_id": "DEL659316",
    "player_name": "Oscar Delp",
    "positions": [
      "TE"
    ],
    "team": "NO",
    "age": 22.8,
    "headshot": null
  },
  {
    "player_id": "00-0037252",
    "player_name": "Greg Dulcich",
    "positions": [
      "TE"
    ],
    "team": "MIA",
    "age": 26.1,
    "headshot": "https://static.www.nfl.com/image/upload/f_auto,q_auto/league/kirfnwuge3eam1s0ycne"
  },
  {
    "player_id": "00-0039373",
    "player_name": "Audric Estime",
    "positions": [
      "RB"
    ],
    "team": "NO",
    "age": 22.7,
    "headshot": "https://static.www.nfl.com/image/upload/f_auto,q_auto/league/lcoend1mysjfhl8f4rrt"
  },
  {
    "player_id": "SIM639376",
    "player_name": "Ty Simpson",
    "positions": [
      "QB"
    ],
    "team": "LA",
    "age": 23.4,
    "headshot": null
  },
  {
    "player_id": "00-0040692",
    "player_name": "Jarquez Hunter",
    "positions": [
      "RB"
    ],
    "team": "LA",
    "age": 23.4,
    "headshot": "https://static.www.nfl.com/image/upload/f_auto,q_auto/league/k4mncnazqbnewpg5uwdm"
  },
  {
    "player_id": "00-0040644",
    "player_name": "Trevor Etienne",
    "positions": [
      "RB"
    ],
    "team": "CAR",
    "age": 21.9,
    "headshot": "https://static.www.nfl.com/image/upload/f_auto,q_auto/league/futkvr4juiazofhntj0p"
  },
  {
    "player_id": "00-0038619",
    "player_name": "Andrei Iosivas",
    "positions": [
      "WR"
    ],
    "team": "CIN",
    "age": 26.6,
    "headshot": "https://static.www.nfl.com/image/upload/f_auto,q_auto/league/zvanfldklpds1gp08bsp"
  },
  {
    "player_id": "00-0033923",
    "player_name": "Kareem Hunt",
    "positions": [
      "RB"
    ],
    "team": "FA",
    "age": 30.8,
    "headshot": "https://static.www.nfl.com/image/upload/f_auto,q_auto/league/hktvzf8hiupoycyg1kmc"
  },
  {
    "player_id": "00-0040208",
    "player_name": "Tahj Brooks",
    "positions": [
      "RB"
    ],
    "team": "CIN",
    "age": 24.0,
    "headshot": "https://static.www.nfl.com/image/upload/f_auto,q_auto/league/wi7smnfts8t04wnd0n3p"
  },
  {
    "player_id": "00-0039923",
    "player_name": "J.J. McCarthy",
    "positions": [
      "QB"
    ],
    "team": "MIN",
    "age": 23.3,
    "headshot": "https://static.www.nfl.com/image/upload/f_auto,q_auto/league/omybnfokapjw6jwb5dd3"
  },
  {
    "player_id": "00-0038979",
    "player_name": "Cedric Tillman",
    "positions": [
      "WR"
    ],
    "team": "CLE",
    "age": 26.1,
    "headshot": "https://static.www.nfl.com/image/upload/f_auto,q_auto/league/a4mcdjjl1pkxr3etechx"
  },
  {
    "player_id": "00-0039355",
    "player_name": "Luke McCaffrey",
    "positions": [
      "WR"
    ],
    "team": "WAS",
    "age": 25.1,
    "headshot": "https://static.www.nfl.com/image/upload/f_auto,q_auto/league/iqzscuxu9lxjfhoyxsjg"
  },
  {
    "player_id": "00-0040590",
    "player_name": "Konata Mumpfield",
    "positions": [
      "WR"
    ],
    "team": "LA",
    "age": 23.6,
    "headshot": "https://static.www.nfl.com/image/upload/f_auto,q_auto/league/psy72cl8ko1zp7vkbvga"
  },
  {
    "player_id": "00-0037157",
    "player_name": "Bam Knight",
    "positions": [
      "RB"
    ],
    "team": "ARI",
    "age": 25.1,
    "headshot": "https://static.www.nfl.com/image/upload/f_auto,q_auto/league/mjxnlzlnnwlfqayeybut"
  },
  {
    "player_id": "00-0037837",
    "player_name": "Calvin Austin III",
    "positions": [
      "WR"
    ],
    "team": "NYG",
    "age": 27.2,
    "headshot": "https://static.www.nfl.com/image/private/f_auto,q_auto/league/qlt6ztqcbu0uzad6aavt"
  },
  {
    "player_id": "BLA097235",
    "player_name": "Kaelon Black",
    "positions": [
      "RB"
    ],
    "team": "SF",
    "age": 24.6,
    "headshot": null
  },
  {
    "player_id": "00-0040237",
    "player_name": "Tez Johnson",
    "positions": [
      "WR"
    ],
    "team": "TB",
    "age": 24.0,
    "headshot": "https://static.www.nfl.com/image/upload/f_auto,q_auto/league/zjtu1bcayjh9qunkxs9z"
  },
  {
    "player_id": "00-0036972",
    "player_name": "Mac Jones",
    "positions": [
      "QB"
    ],
    "team": "SF",
    "age": 27.7,
    "headshot": "https://static.www.nfl.com/image/upload/f_auto,q_auto/league/v5sg1z9qvdpjeapblndz"
  },
  {
    "player_id": "00-0039746",
    "player_name": "Will Shipley",
    "positions": [
      "RB"
    ],
    "team": "PHI",
    "age": 23.7,
    "headshot": "https://static.www.nfl.com/image/upload/f_auto,q_auto/league/rdps3spkhbztc2mbd6ty"
  },
  {
    "player_id": "00-0040646",
    "player_name": "Jalen Royals",
    "positions": [
      "WR"
    ],
    "team": "KC",
    "age": 23.2,
    "headshot": "https://static.www.nfl.com/image/upload/f_auto,q_auto/league/x1t7v5nl0zwkjqucmnfw"
  },
  {
    "player_id": "00-0033110",
    "player_name": "Tyler Higbee",
    "positions": [
      "TE"
    ],
    "team": "LA",
    "age": 33.4,
    "headshot": "https://static.www.nfl.com/image/upload/f_auto,q_auto/league/x1d4osiefibd04df6gow"
  },
  {
    "player_id": "00-0037741",
    "player_name": "Jahan Dotson",
    "positions": [
      "WR"
    ],
    "team": "ATL",
    "age": 26.2,
    "headshot": "https://static.www.nfl.com/image/upload/f_auto,q_auto/league/dbtou5ln1kwjutixywie"
  },
  {
    "player_id": "00-0038558",
    "player_name": "Darnell Washington",
    "positions": [
      "TE"
    ],
    "team": "PIT",
    "age": 24.8,
    "headshot": "https://static.www.nfl.com/image/upload/f_auto,q_auto/league/nza9bxmg2tdtg7wldjct"
  },
  {
    "player_id": "00-0034791",
    "player_name": "Nick Chubb",
    "positions": [
      "RB"
    ],
    "team": "FA",
    "age": 30.4,
    "headshot": "https://static.www.nfl.com/image/upload/f_auto,q_auto/league/h5y74trx6l8ivpkbmrkt"
  },
  {
    "player_id": "00-0036637",
    "player_name": "Noah Gray",
    "positions": [
      "TE"
    ],
    "team": "KC",
    "age": 27.1,
    "headshot": "https://static.www.nfl.com/image/upload/f_auto,q_auto/league/yugngcrdfxh0nwzl4zwp"
  },
  {
    "player_id": "00-0036924",
    "player_name": "Michael Carter",
    "positions": [
      "RB"
    ],
    "team": "TEN",
    "age": 27.0,
    "headshot": "https://static.www.nfl.com/image/upload/f_auto,q_auto/league/e1y7zhd7w3xbthodfa3m"
  },
  {
    "player_id": "00-0033699",
    "player_name": "Austin Ekeler",
    "positions": [
      "RB"
    ],
    "team": "FA",
    "age": 31.0,
    "headshot": "https://static.www.nfl.com/image/upload/f_auto,q_auto/league/sldndpn2zwt4uhkj2zks"
  },
  {
    "player_id": "00-0040739",
    "player_name": "Elijah Arroyo",
    "positions": [
      "TE"
    ],
    "team": "SEA",
    "age": 23.1,
    "headshot": "https://static.www.nfl.com/image/upload/f_auto,q_auto/league/dwlyrxi2yxowfj4abtoa"
  },
  {
    "player_id": "JOL735174",
    "player_name": "Justin Joly",
    "positions": [
      "TE"
    ],
    "team": "DEN",
    "age": 21.9,
    "headshot": null
  },
  {
    "player_id": "00-0040581",
    "player_name": "Dont'e Thornton Jr.",
    "positions": [
      "WR"
    ],
    "team": "LV",
    "age": 23.5,
    "headshot": "https://static.www.nfl.com/image/upload/f_auto,q_auto/league/hlxztd3lpjaxtzojuxwh"
  },
  {
    "player_id": "DOU210628",
    "player_name": "Caleb Douglas",
    "positions": [
      "WR"
    ],
    "team": "MIA",
    "age": 22.7,
    "headshot": null
  },
  {
    "player_id": "00-0036945",
    "player_name": "Justin Fields",
    "positions": [
      "QB"
    ],
    "team": "KC",
    "age": 27.2,
    "headshot": "https://static.www.nfl.com/image/upload/f_auto,q_auto/league/fbteankooq2c33yquq2j"
  },
  {
    "player_id": "00-0038621",
    "player_name": "DeMario Douglas",
    "positions": [
      "WR"
    ],
    "team": "NE",
    "age": 25.4,
    "headshot": "https://static.www.nfl.com/image/upload/f_auto,q_auto/league/almsm6nmovpasu8ts9u3"
  },
  {
    "player_id": "BEC122142",
    "player_name": "Carson Beck",
    "positions": [
      "QB"
    ],
    "team": "ARI",
    "age": 23.5,
    "headshot": null
  },
  {
    "player_id": "00-0035208",
    "player_name": "Olamide Zaccheaus",
    "positions": [
      "WR"
    ],
    "team": "ATL",
    "age": 28.8,
    "headshot": "https://static.www.nfl.com/image/upload/f_auto,q_auto/league/ucpai2odeunecbe6o1dj"
  },
  {
    "player_id": "HEI114391",
    "player_name": "Eli Heidenreich",
    "positions": [
      "RB"
    ],
    "team": "PIT",
    "age": 22.8,
    "headshot": null
  },
  {
    "player_id": "00-0039164",
    "player_name": "Anthony Richardson Sr.",
    "positions": [
      "QB"
    ],
    "team": "IND",
    "age": 24.0,
    "headshot": "https://static.www.nfl.com/image/upload/f_auto,q_auto/league/wrddeyklfcgk9qybgofq"
  },
  {
    "player_id": "LAN016345",
    "player_name": "Bryce Lance",
    "positions": [
      "WR"
    ],
    "team": "NO",
    "age": 24.7,
    "headshot": null
  },
  {
    "player_id": "00-0036988",
    "player_name": "Joshua Palmer",
    "positions": [
      "WR"
    ],
    "team": "BUF",
    "age": 26.7,
    "headshot": "https://static.www.nfl.com/image/upload/f_auto,q_auto/league/woswdfrtxnsfgzsjvsxx"
  },
  {
    "player_id": "00-0038618",
    "player_name": "Xavier Hutchinson",
    "positions": [
      "WR"
    ],
    "team": "HOU",
    "age": 26.0,
    "headshot": "https://static.www.nfl.com/image/upload/f_auto,q_auto/league/hv3mfhadliph08b4pl4s"
  },
  {
    "player_id": "THO495568",
    "player_name": "Brenen Thompson",
    "positions": [
      "WR"
    ],
    "team": "LAC",
    "age": 22.8,
    "headshot": null
  },
  {
    "player_id": "00-0037666",
    "player_name": "Jalen Tolbert",
    "positions": [
      "WR"
    ],
    "team": "MIA",
    "age": 27.2,
    "headshot": "https://static.www.nfl.com/image/upload/f_auto,q_auto/league/pif5ffxlibkfp90k1sj4"
  },
  {
    "player_id": "00-0039356",
    "player_name": "Ja'Tavion Sanders",
    "positions": [
      "TE"
    ],
    "team": "CAR",
    "age": 23.1,
    "headshot": "https://static.www.nfl.com/image/upload/f_auto,q_auto/league/le2akm1cbou170ioctxl"
  },
  {
    "player_id": "00-0031610",
    "player_name": "Darren Waller",
    "positions": [
      "TE"
    ],
    "team": "FA",
    "age": 33.7,
    "headshot": "https://static.www.nfl.com/image/upload/f_auto,q_auto/league/loyehiyzcu2lexjk7plq"
  },
  {
    "player_id": "00-0040164",
    "player_name": "Jaylin Lane",
    "positions": [
      "WR"
    ],
    "team": "WAS",
    "age": 24.0,
    "headshot": "https://static.www.nfl.com/image/upload/f_auto,q_auto/league/ozgin9atyuq92buo2eoa"
  },
  {
    "player_id": "00-0037614",
    "player_name": "John Metchie III",
    "positions": [
      "WR"
    ],
    "team": "CAR",
    "age": 25.8,
    "headshot": "https://static.www.nfl.com/image/upload/f_auto,q_auto/league/u7ir1sy2vrpidvwpndqd"
  },
  {
    "player_id": "00-0039066",
    "player_name": "Michael Mayer",
    "positions": [
      "TE"
    ],
    "team": "LV",
    "age": 24.9,
    "headshot": "https://static.www.nfl.com/image/upload/f_auto,q_auto/league/crb4nzumiww6ftxcyiqm"
  },
  {
    "player_id": "00-0040466",
    "player_name": "Raheim Sanders",
    "positions": [
      "RB"
    ],
    "team": "CLE",
    "age": 23.9,
    "headshot": "https://static.www.nfl.com/image/upload/f_auto,q_auto/league/jkty8m7iqcjjfmrxhfub"
  },
  {
    "player_id": "00-0040009",
    "player_name": "Savion Williams",
    "positions": [
      "WR"
    ],
    "team": "GB",
    "age": 24.5,
    "headshot": "https://static.www.nfl.com/image/upload/f_auto,q_auto/league/fkhkv59ojmqixfxkzmno"
  },
  {
    "player_id": "00-0037258",
    "player_name": "Dameon Pierce",
    "positions": [
      "RB"
    ],
    "team": "PHI",
    "age": 26.2,
    "headshot": "https://static.www.nfl.com/image/upload/f_auto,q_auto/league/lifrupicniyrosy1vj9c"
  },
  {
    "player_id": "00-0039405",
    "player_name": "Jawhar Jordan",
    "positions": [
      "RB"
    ],
    "team": "HOU",
    "age": 26.8,
    "headshot": "https://static.www.nfl.com/image/upload/f_auto,q_auto/league/kyopmcyi4hzko3cxiaxy"
  },
  {
    "player_id": "00-0036628",
    "player_name": "John Bates",
    "positions": [
      "TE"
    ],
    "team": "WAS",
    "age": 28.5,
    "headshot": "https://static.www.nfl.com/image/upload/f_auto,q_auto/league/edpnkleev10rpzfgjakv"
  },
  {
    "player_id": "00-0039912",
    "player_name": "Ben Sinnott",
    "positions": [
      "TE"
    ],
    "team": "WAS",
    "age": 23.9,
    "headshot": "https://static.www.nfl.com/image/upload/f_auto,q_auto/league/zwjmu9wyutlpkace9ukf"
  },
  {
    "player_id": "00-0036328",
    "player_name": "Antonio Gibson",
    "positions": [
      "RB"
    ],
    "team": "FA",
    "age": 27.9,
    "headshot": "https://static.www.nfl.com/image/upload/f_auto,q_auto/league/j7ixpkm7u4tdoqwzmbt4"
  },
  {
    "player_id": "00-0037742",
    "player_name": "Treylon Burks",
    "positions": [
      "WR"
    ],
    "team": "WAS",
    "age": 26.2,
    "headshot": "https://static.www.nfl.com/image/upload/f_auto,q_auto/league/dkgspszcaouw7lkpjmio"
  },
  {
    "player_id": "00-0036290",
    "player_name": "Cole Kmet",
    "positions": [
      "TE"
    ],
    "team": "CHI",
    "age": 27.2,
    "headshot": "https://static.www.nfl.com/image/upload/f_auto,q_auto/league/ysnui8mzlu2fo70ub0yt"
  },
  {
    "player_id": "COL362413",
    "player_name": "Kevin Coleman Jr.",
    "positions": [
      "WR"
    ],
    "team": "MIA",
    "age": 22.7,
    "headshot": null
  },
  {
    "player_id": "ALL092954",
    "player_name": "Cyrus Allen",
    "positions": [
      "WR"
    ],
    "team": "KC",
    "age": 23.3,
    "headshot": null
  },
  {
    "player_id": "00-0037801",
    "player_name": "KaVontae Turpin",
    "positions": [
      "WR"
    ],
    "team": "DAL",
    "age": 29.8,
    "headshot": "https://static.www.nfl.com/image/upload/f_auto,q_auto/league/cgjwzierootp8gjem5oe"
  },
  {
    "player_id": "DAN490797",
    "player_name": "CJ Daniels",
    "positions": [
      "WR"
    ],
    "team": "LA",
    "age": 24.4,
    "headshot": null
  },
  {
    "player_id": "00-0035689",
    "player_name": "Dawson Knox",
    "positions": [
      "TE"
    ],
    "team": "BUF",
    "age": 29.5,
    "headshot": "https://static.www.nfl.com/image/upload/f_auto,q_auto/league/mswln16dmfhi7m7pzh7q"
  },
  {
    "player_id": "00-0039757",
    "player_name": "Terrell Jennings",
    "positions": [
      "RB"
    ],
    "team": "NE",
    "age": 25.4,
    "headshot": "https://static.www.nfl.com/image/upload/f_auto,q_auto/league/iddgabjbju6ye5s9mmjg"
  },
  {
    "player_id": "00-0033307",
    "player_name": "Kendrick Bourne",
    "positions": [
      "WR"
    ],
    "team": "ARI",
    "age": 30.8,
    "headshot": "https://static.www.nfl.com/image/upload/f_auto,q_auto/league/rroh157jvpywprbfn3vx"
  },
  {
    "player_id": "BEN601117",
    "player_name": "Malik Benson",
    "positions": [
      "WR"
    ],
    "team": "LV",
    "age": 23.6,
    "headshot": null
  },
  {
    "player_id": "00-0031503",
    "player_name": "Jameis Winston",
    "positions": [
      "QB"
    ],
    "team": "NYG",
    "age": 32.4,
    "headshot": "https://static.www.nfl.com/image/upload/f_auto,q_auto/league/vwikoroqsyf8iemlrohb"
  },
  {
    "player_id": "KLU066027",
    "player_name": "Cade Klubnik",
    "positions": [
      "QB"
    ],
    "team": "NYJ",
    "age": 22.6,
    "headshot": null
  },
  {
    "player_id": "00-0039398",
    "player_name": "Joe Milton III",
    "positions": [
      "QB"
    ],
    "team": "DAL",
    "age": 26.2,
    "headshot": "https://static.www.nfl.com/image/upload/f_auto,q_auto/league/tsj9lobse1gxzanf39dt"
  },
  {
    "player_id": "00-0036849",
    "player_name": "Tutu Atwell",
    "positions": [
      "WR"
    ],
    "team": "MIA",
    "age": 26.6,
    "headshot": "https://static.www.nfl.com/image/upload/f_auto,q_auto/league/twlslcaa7c2wblveaafu"
  },
  {
    "player_id": "00-0030061",
    "player_name": "Zach Ertz",
    "positions": [
      "TE"
    ],
    "team": "FA",
    "age": 35.5,
    "headshot": "https://static.www.nfl.com/image/upload/f_auto,q_auto/league/xktmmeumuoglbuam75iz"
  },
  {
    "player_id": "00-0032464",
    "player_name": "Kalif Raymond",
    "positions": [
      "WR"
    ],
    "team": "CHI",
    "age": 31.8,
    "headshot": "https://static.www.nfl.com/image/upload/f_auto,q_auto/league/e5z8bskwg89hqtsjwwgj"
  },
  {
    "player_id": "00-0040651",
    "player_name": "Damien Martinez",
    "positions": [
      "RB"
    ],
    "team": "GB",
    "age": 22.3,
    "headshot": "https://static.www.nfl.com/image/upload/f_auto,q_auto/league/cx7us9eu6fa8rmp6yszj"
  },
  {
    "player_id": "RAR148318",
    "player_name": "Eli Raridon",
    "positions": [
      "TE"
    ],
    "team": "NE",
    "age": 22.3,
    "headshot": null
  },
  {
    "player_id": "THO417520",
    "player_name": "Zavion Thomas",
    "positions": [
      "WR"
    ],
    "team": "CHI",
    "age": 21.7,
    "headshot": null
  },
  {
    "player_id": "00-0035644",
    "player_name": "Noah Fant",
    "positions": [
      "TE"
    ],
    "team": "NO",
    "age": 28.5,
    "headshot": "https://static.www.nfl.com/image/upload/f_auto,q_auto/league/s4idwk38z6bin9lnnw9f"
  },
  {
    "player_id": "00-0040154",
    "player_name": "Tai Felton",
    "positions": [
      "WR"
    ],
    "team": "MIN",
    "age": 23.2,
    "headshot": "https://static.www.nfl.com/image/upload/f_auto,q_auto/league/j7vkt74xeefchpraibnx"
  },
  {
    "player_id": "00-0039144",
    "player_name": "Luke Musgrave",
    "positions": [
      "TE"
    ],
    "team": "GB",
    "age": 25.7,
    "headshot": "https://static.www.nfl.com/image/upload/f_auto,q_auto/league/erqld7keza48co6umuaa"
  },
  {
    "player_id": "00-0038115",
    "player_name": "Daniel Bellinger",
    "positions": [
      "TE"
    ],
    "team": "TEN",
    "age": 25.7,
    "headshot": "https://static.www.nfl.com/image/upload/f_auto,q_auto/league/hu3gywcwp2rlsefvawh1"
  },
  {
    "player_id": "BUR271406",
    "player_name": "Deion Burks",
    "positions": [
      "WR"
    ],
    "team": "IND",
    "age": 23.4,
    "headshot": null
  },
  {
    "player_id": "00-0033858",
    "player_name": "Jonnu Smith",
    "positions": [
      "TE"
    ],
    "team": "FA",
    "age": 30.7,
    "headshot": "https://static.www.nfl.com/image/upload/f_auto,q_auto/league/egd6llghj3n5wfdrqacw"
  },
  {
    "player_id": "00-0026158",
    "player_name": "Joe Flacco",
    "positions": [
      "QB"
    ],
    "team": "CIN",
    "age": 41.3,
    "headshot": "https://static.www.nfl.com/image/upload/f_auto,q_auto/league/vbqptn8emdlbeaz1kvmx"
  },
  {
    "player_id": "00-0032268",
    "player_name": "Marcus Mariota",
    "positions": [
      "QB"
    ],
    "team": "WAS",
    "age": 32.6,
    "headshot": "https://static.www.nfl.com/image/upload/f_auto,q_auto/league/b9ribxqudeehvmjlw0va"
  },
  {
    "player_id": "MIL303300",
    "player_name": "Jam Miller",
    "positions": [
      "RB"
    ],
    "team": "NE",
    "age": 22.1,
    "headshot": null
  },
  {
    "player_id": "00-0040021",
    "player_name": "Phil Mafah",
    "positions": [
      "RB"
    ],
    "team": "DAL",
    "age": 23.6,
    "headshot": "https://static.www.nfl.com/image/upload/f_auto,q_auto/league/k1njpmidvzsbe9tithio"
  },
  {
    "player_id": "00-0039021",
    "player_name": "Roschon Johnson",
    "positions": [
      "RB"
    ],
    "team": "CHI",
    "age": 25.3,
    "headshot": "https://static.www.nfl.com/image/upload/f_auto,q_auto/league/gxzw5kntjivjixre9whh"
  },
  {
    "player_id": "00-0035289",
    "player_name": "Gardner Minshew II",
    "positions": [
      "QB"
    ],
    "team": "ARI",
    "age": 30.0,
    "headshot": "https://static.www.nfl.com/image/upload/f_auto,q_auto/league/lggwtoj1m0jxxiawtzpw"
  },
  {
    "player_id": "00-0039041",
    "player_name": "Elijah Higgins",
    "positions": [
      "TE"
    ],
    "team": "ARI",
    "age": 25.6,
    "headshot": "https://static.www.nfl.com/image/upload/f_auto,q_auto/league/yjvdxmqromyt64w89bhq"
  },
  {
    "player_id": "KLE258860",
    "player_name": "Marlin Klein",
    "positions": [
      "TE"
    ],
    "team": "HOU",
    "age": 23.7,
    "headshot": null
  },
  {
    "player_id": "00-0039792",
    "player_name": "Devontez Walker",
    "positions": [
      "WR"
    ],
    "team": "BAL",
    "age": 24.9,
    "headshot": "https://static.www.nfl.com/image/upload/f_auto,q_auto/league/d8qrpenynncwink7dqs2"
  },
  {
    "player_id": "ROU550040",
    "player_name": "Sam Roush",
    "positions": [
      "TE"
    ],
    "team": "CHI",
    "age": 22.7,
    "headshot": null
  },
  {
    "player_id": "00-0040206",
    "player_name": "Riley Leonard",
    "positions": [
      "QB"
    ],
    "team": "IND",
    "age": 23.7,
    "headshot": "https://static.www.nfl.com/image/upload/f_auto,q_auto/league/vzdcrhp4p5kjmuhn7yay"
  }
]