{
  "00-0036997": {
    "player_name": "Javonte Williams",
    "summary": "The Cowboys and RB Javonte Williams have agreed to terms on a 3-year, $24M deal worth $8M per year, keeping him in Dallas after a breakout season.",
    "sources": [
      "https://www.reddit.com/r/DynastyFF/comments/1rb3903/the_cowboys_and_standout_rb_javonte_williams_have/"
    ],
    "article_count": 1,
    "generated_at": "2026-03-13T15:07:23"
  },
  "00-0038134": {
    "player_name": "Kenneth Walker III",
    "summary": "Kenneth Walker III, formerly of the Seahawks, is signing with the Chiefs.",
    "sources": [
      "https://www.reddit.com/r/DynastyFF/comments/1rp4rwi/splash_the_chiefs_are_signing_super_bowl_mvp/",
      "https://www.reddit.com/r/DynastyFF/comments/1riu0cw/giants_expected_to_make_strong_push_for_kenneth/",
      "https://www.reddit.com/r/DynastyFF/comments/1rmv3wp/chiefs_to_make_a_play_for_kenneth_walker_along/",
      "https://www.reddit.com/r/DynastyFF/comments/1r74z0d/its_unlikely_the_seahawks_will_use_their/"
    ],
    "article_count": 4,
    "generated_at": "2026-03-13T15:07:25"
  },
  "00-0034827": {
    "player_name": "DJ Moore",
    "summary": "The Bears are trading wide receiver DJ Moore to the Bills, giving Josh Allen a new weapon.",
    "sources": [
      "https://www.reddit.com/r/DynastyFF/comments/1rlmi6f/jordan_schultz_breaking_the_bears_are_trading/"
    ],
    "article_count": 1,
    "generated_at": "2026-03-13T15:07:25"
  },
  "00-0037838": {
    "player_name": "Isaiah Likely",
    "summary": "The Giants are signing former Ravens TE Isaiah Likely to a 3-year, $40M contract with upside to $47.5M.",
    "sources": [
      "https://www.reddit.com/r/DynastyFF/comments/1rp5m16/breaking_the_giants_are_signing_former_ravens_te/"
    ],
    "article_count": 1,
    "generated_at": "2026-03-13T15:07:25"
  },
  "00-0035685": {
    "player_name": "David Montgomery",
    "summary": "David Montgomery has been traded to the Houston Texans.",
    "sources": [
      "https://www.reddit.com/r/DynastyFF/comments/1riwpsm/pelissero_david_montgomery_traded_to_the_texans/"
    ],
    "article_count": 1,
    "generated_at": "2026-03-13T15:07:25"
  },
  "00-0037816": {
    "player_name": "Romeo Doubs",
    "summary": "The Patriots are signing former Packers WR Romeo Doubs.",
    "sources": [
      "https://www.reddit.com/r/DynastyFF/comments/1rq4rvf/breaking_the_patriots_are_signing_former_packers/"
    ],
    "article_count": 1,
    "generated_at": "2026-03-13T15:07:25"
  },
  "00-0035228": {
    "player_name": "Kyler Murray",
    "summary": "Kyler Murray is signing a one-year deal with the Minnesota Vikings after being released by the Arizona Cardinals.",
    "sources": [
      "https://www.reddit.com/r/DynastyFF/comments/1rs586b/former_cardinals_qb_kyler_murray_is_signing_a/",
      "https://www.reddit.com/r/DynastyFF/comments/1rk1b75/kyler_murray_to_officially_be_released_by_the/",
      "https://www.reddit.com/r/DynastyFF/comments/1rrdi8w/pelissero_per_kyler_murrays_agent_erik_burkhardt/"
    ],
    "article_count": 3,
    "generated_at": "2026-03-13T15:07:27"
  },
  "00-0031408": {
    "player_name": "Mike Evans",
    "summary": "Mike Evans is expected to sign a three-year deal with the San Francisco 49ers.",
    "sources": [
      "https://www.reddit.com/r/DynastyFF/comments/1rp8g2s/espn_sources_former_buccaneers_sixtime_probowl_wr/",
      "https://www.reddit.com/r/DynastyFF/comments/1r7jhm6/mike_evans_plans_to_play_in_2026_and_will_explore/"
    ],
    "article_count": 2,
    "generated_at": "2026-03-13T15:07:29"
  },
  "00-0038128": {
    "player_name": "Malik Willis",
    "summary": "The Dolphins are signing Packers QB Malik Willis to a 3-year, $67.5 million deal with $45 million fully guaranteed.",
    "sources": [
      "https://www.reddit.com/r/DynastyFF/comments/1rdkaf2/dolphins_gm_joneric_sullivan_on_malik_willis_any/",
      "https://www.reddit.com/r/DynastyFF/comments/1rp5jxe/rapoport_the_dolphins_are_signing_packers_qb/",
      "https://www.reddit.com/r/DynastyFF/comments/1ronsjk/woelfel_it_appears_the_arizona_cardinals_have/"
    ],
    "article_count": 3,
    "generated_at": "2026-03-13T15:07:32"
  },
  "00-0038454": {
    "player_name": "Keaton Mitchell",
    "summary": "Former Ravens RB Keaton Mitchell is signing with the Chargers on a two-year, $9.25 million deal that includes $5 million fully guaranteed.",
    "sources": [
      "https://www.reddit.com/r/DynastyFF/comments/1rroctk/former_ravens_rb_keaton_mitchell_is_signing_with/"
    ],
    "article_count": 1,
    "generated_at": "2026-03-13T15:07:32"
  },
  "00-0037263": {
    "player_name": "Tyler Allgeier",
    "summary": "Tyler Allgeier has agreed to a 2-year, $12.25 million deal with the Arizona Cardinals.",
    "sources": [
      "https://www.reddit.com/r/DynastyFF/comments/1rp76ow/tyler_allgeier_to_arizona_2_years_1225_million/"
    ],
    "article_count": 1,
    "generated_at": "2026-03-13T15:07:32"
  },
  "00-0038951": {
    "player_name": "Sean Tucker",
    "summary": "The Buccaneers will not place a restricted tender on RB Sean Tucker, making him a free agent. Tucker rushed for 320 yards and seven touchdowns last year.",
    "sources": [
      "https://www.reddit.com/r/DynastyFF/comments/1rl1w8e/no_restricted_tender_for_bucs_rb_sean_tucker_per/"
    ],
    "article_count": 1,
    "generated_at": "2026-03-13T15:07:32"
  },
  "00-0036139": {
    "player_name": "Rico Dowdle",
    "summary": "Rico Dowdle is reportedly set to sign with the Pittsburgh Steelers.",
    "sources": [
      "https://www.reddit.com/r/DynastyFF/comments/1rpg94j/schultz_rico_dowdle_to_sign_with_the_steelers/"
    ],
    "article_count": 1,
    "generated_at": "2026-03-13T15:07:32"
  },
  "00-0033119": {
    "player_name": "Jacoby Brissett",
    "summary": "According to John Gambadoro, Jacoby Brissett will be the Cardinals' starting QB for the 2026 season, with Gardner Minshew serving as his backup.",
    "sources": [
      "https://www.reddit.com/r/DynastyFF/comments/1rpctnp/john_gambadoro_jacoby_brissett_will_be_the/"
    ],
    "article_count": 1,
    "generated_at": "2026-03-13T15:07:32"
  },
  "00-0035289": {
    "player_name": "Gardner Minshew",
    "summary": "According to John Gambadoro, Jacoby Brissett will be the Cardinals' starting QB for the 2026 season, with Gardner Minshew serving as his backup.",
    "sources": [
      "https://www.reddit.com/r/DynastyFF/comments/1rpctnp/john_gambadoro_jacoby_brissett_will_be_the/"
    ],
    "article_count": 1,
    "generated_at": "2026-03-13T15:07:32"
  },
  "00-0031588": {
    "player_name": "Stefon Diggs",
    "summary": "Stefon Diggs is set to be released by the Patriots, according to Pelissero.",
    "sources": [
      "https://www.reddit.com/r/DynastyFF/comments/1rkwld2/breaking_news_pelissero_stefon_diggs_to_be/"
    ],
    "article_count": 1,
    "generated_at": "2026-03-13T15:07:32"
  },
  "00-0033040": {
    "player_name": "Tyreek Hill",
    "summary": "The Miami Dolphins have released wide receiver Tyreek Hill.",
    "sources": [
      "https://www.reddit.com/r/DynastyFF/comments/1r6eetk/schefter_dolphins_release_tyreek_hill/"
    ],
    "article_count": 1,
    "generated_at": "2026-03-13T15:07:32"
  },
  "00-0037664": {
    "player_name": "Alec Pierce",
    "summary": "Alec Pierce agreed to a 4-year, $114M deal to remain with the Indianapolis Colts, making him the highest-paid free agent receiver in NFL history.",
    "sources": [
      "https://www.reddit.com/r/DynastyFF/comments/1rkvko7/alec_pierce_to_test_free_agency_i_love_indy_but/",
      "https://www.reddit.com/r/DynastyFF/comments/1rp4dhu/ian_rapoport_free_agent_wr_alec_pierce_has_agreed/"
    ],
    "article_count": 2,
    "generated_at": "2026-03-13T15:07:34"
  },
  "00-0040784": {
    "player_name": "Quinshon Judkins",
    "summary": "Browns RB Quinshon Judkins is out of his boot and will be ready for training camp, according to GM Andrew Berry.",
    "sources": [
      "https://www.reddit.com/r/DynastyFF/comments/1rdqm4f/browns_rb_quinshon_judkins_is_out_of_his_boot_and/"
    ],
    "article_count": 1,
    "generated_at": "2026-03-13T15:07:34"
  },
  "00-0037256": {
    "player_name": "Rachaad White",
    "summary": "The Commanders are signing former Bucs RB Rachaad White to a one-year deal, reuniting him with his college quarterback Jayden Daniels.",
    "sources": [
      "https://www.reddit.com/r/DynastyFF/comments/1rrzsvq/commanders_are_signing_former_bucs_rb_rachaad/"
    ],
    "article_count": 1,
    "generated_at": "2026-03-13T15:07:34"
  },
  "00-0038797": {
    "player_name": "Emanuel Wilson",
    "summary": "The Seahawks are signing former Packers RB Emanuel Wilson to a 1-year deal worth up to $2.1M.",
    "sources": [
      "https://www.reddit.com/r/DynastyFF/comments/1rs36bx/the_seahawks_are_signing_former_packers_rb/"
    ],
    "article_count": 1,
    "generated_at": "2026-03-13T15:07:34"
  },
  "00-0039164": {
    "player_name": "Anthony Richardson Sr.",
    "summary": "The Colts have given quarterback Anthony Richardson permission to seek a trade.",
    "sources": [
      "https://www.reddit.com/r/DynastyFF/comments/1rfgqnf/the_colts_have_given_anthony_richardson/"
    ],
    "article_count": 1,
    "generated_at": "2026-03-13T15:07:34"
  },
  "00-0036973": {
    "player_name": "Travis Etienne Jr.",
    "summary": "Travis Etienne has signed with the Saints.",
    "sources": [
      "https://www.reddit.com/r/DynastyFF/comments/1rp7iv0/travis_etienne_signs_with_saints/"
    ],
    "article_count": 1,
    "generated_at": "2026-03-13T15:07:34"
  },
  "00-0037197": {
    "player_name": "Isiah Pacheco",
    "summary": "The Lions are signing RB Isiah Pacheco, according to Tom Pelissero.",
    "sources": [
      "https://www.reddit.com/r/DynastyFF/comments/1rq2qu1/the_lions_are_signing_rb_isiah_pacheco_tom/"
    ],
    "article_count": 1,
    "generated_at": "2026-03-13T15:07:34"
  },
  "00-0036893": {
    "player_name": "Najee Harris",
    "summary": "Najee Harris is reportedly looking outstanding in his recovery five months after Achilles surgery, running with ease at 15 mph.",
    "sources": [
      "https://www.reddit.com/r/DynastyFF/comments/1rcqxsi/najee_harris_looking_outstanding_5_months_post_op/"
    ],
    "article_count": 1,
    "generated_at": "2026-03-13T15:07:34"
  },
  "00-0039855": {
    "player_name": "Jalen McMillan",
    "summary": "Buccaneers head coach Todd Bowles referred to wide receiver Jalen McMillan as a \"workhorse\" and praised his potential, noting he looked good in a limited role at the end of the season after recovering from a neck injury in 2025.",
    "sources": [
      "https://www.reddit.com/r/DynastyFF/comments/1ricb8a/todd_bowles_calls_jalen_mcmillan_workhorse_some/"
    ],
    "article_count": 1,
    "generated_at": "2026-03-13T15:07:34"
  },
  "00-0037545": {
    "player_name": "Rashid Shaheed",
    "summary": "The Seahawks are re-signing WR Rashid Shaheed to a three-year, $51 million deal that includes $34.7 million guaranteed.",
    "sources": [
      "https://www.reddit.com/r/DynastyFF/comments/1ronvco/fowler_espn_the_raiders_are_expected_to_make_a/",
      "https://www.reddit.com/r/DynastyFF/comments/1rpeukv/seahawks_are_bringing_back_wr_rashid_shaheed_on_a/"
    ],
    "article_count": 2,
    "generated_at": "2026-03-13T15:07:36"
  },
  "00-0033897": {
    "player_name": "Joe Mixon",
    "summary": "The Houston Texans released running back Joe Mixon.",
    "sources": [
      "https://www.reddit.com/r/DynastyFF/comments/1rmpgea/source_texans_released_rb_joe_mixon/",
      "https://www.reddit.com/r/DynastyFF/comments/1rduy1n/its_amazing_nick_caserio_said_today_he_thinks_joe/"
    ],
    "article_count": 2,
    "generated_at": "2026-03-13T15:07:37"
  },
  "00-0034351": {
    "player_name": "Dallas Goedert",
    "summary": "According to Matthew Berry, tight end Dallas Goedert will definitely be moving on from the Eagles.",
    "sources": [
      "https://www.reddit.com/r/DynastyFF/comments/1rj22ff/dallas_goedert_will_definitely_be_moving_on_from/"
    ],
    "article_count": 1,
    "generated_at": "2026-03-13T15:07:37"
  },
  "00-0037247": {
    "player_name": "George Pickens",
    "summary": "NFL Network's Ian Rapoport reports that he doesn't expect George Pickens to report to the Cowboys facility unless and until there is a long-term deal in place.",
    "sources": [
      "https://www.reddit.com/r/DynastyFF/comments/1rgqllo/nfl_networks_ian_rapoport_reports_he_doesnt/"
    ],
    "article_count": 1,
    "generated_at": "2026-03-13T15:07:37"
  },
  "00-0037809": {
    "player_name": "Chig Okonkwo",
    "summary": "Chig Okonkwo is joining the Washington Commanders.",
    "sources": [
      "https://www.reddit.com/r/DynastyFF/comments/1rr3580/garafolo_chig_okonkwo_to_commanders/"
    ],
    "article_count": 1,
    "generated_at": "2026-03-13T15:07:37"
  },
  "00-0036309": {
    "player_name": "Darnell Mooney",
    "summary": "The Falcons are planning to release WR Darnell Mooney, who will count $18.4M against the salary cap. Mooney, 28, has averaged better than 13 yards per catch in each of the last three seasons.",
    "sources": [
      "https://www.reddit.com/r/DynastyFF/comments/1rlhs5k/the_falcons_are_planning_to_release_wr_darnell/"
    ],
    "article_count": 1,
    "generated_at": "2026-03-13T15:07:37"
  },
  "00-0036972": {
    "player_name": "Mac Jones",
    "summary": "Multiple teams have called the San Francisco 49ers about QB Mac Jones, but interested parties describe the 49ers' asking price as 'astronomical.'",
    "sources": [
      "https://www.reddit.com/r/DynastyFF/comments/1rq5egn/russini_a_few_teams_have_called_the_san_francisco/"
    ],
    "article_count": 1,
    "generated_at": "2026-03-13T15:07:37"
  },
  "00-0038611": {
    "player_name": "Chris Rodriguez Jr.",
    "summary": "Chris Rodriguez Jr. is reportedly set to sign with the Jacksonville Jaguars.",
    "sources": [
      "https://www.reddit.com/r/DynastyFF/comments/1rr6mld/schultz_chris_rodriguez_jr_to_sign_with_the/"
    ],
    "article_count": 1,
    "generated_at": "2026-03-13T15:07:37"
  },
  "00-0038120": {
    "player_name": "Breece Hall",
    "summary": "The New York Jets are placing the $14.293 million franchise tag on Breece Hall while the two sides continue negotiating a long-term deal.",
    "sources": [
      "https://www.reddit.com/r/DynastyFF/comments/1rjtr0t/tagged_as_the_jets_and_rb_breece_hall_continue_to/",
      "https://www.reddit.com/r/DynastyFF/comments/1rdnu49/moughey_breece_hall_to_be_tagged_if_not_extended/"
    ],
    "article_count": 2,
    "generated_at": "2026-03-13T15:07:40"
  },
  "00-0033873": {
    "player_name": "Patrick Mahomes",
    "summary": "The Kansas City Chiefs restructured Patrick Mahomes' contract, lowering his salary cap number from $78.2 million to $34.65 million for the upcoming season and creating $43.56 million in salary cap space.",
    "sources": [
      "https://www.reddit.com/r/DynastyFF/comments/1r845yf/the_kansas_city_chiefs_restructured_patrick/"
    ],
    "article_count": 1,
    "generated_at": "2026-03-13T15:07:40"
  },
  "00-0036158": {
    "player_name": "J.K. Dobbins",
    "summary": "JK Dobbins is signing a 2-year deal with the Denver Broncos, per Zac Stevens.",
    "sources": [
      "https://www.reddit.com/r/DynastyFF/comments/1rpa1sj/breaking_news_jk_dobbins_to_sign_a_2year_deal/"
    ],
    "article_count": 1,
    "generated_at": "2026-03-13T15:07:40"
  },
  "00-0039893": {
    "player_name": "Brian Thomas Jr.",
    "summary": "The Jaguars' willingness to trade Brian Thomas Jr. is unclear, with conflicting reports: Adam Schefter reported the team has completely denied any trade interest, while another report claims they are entertaining offers.",
    "sources": [
      "https://www.reddit.com/r/DynastyFF/comments/1rq62n8/adam_schefter_on_pat_mcafee_about_40_mins_ago_ive/",
      "https://www.reddit.com/r/DynastyFF/comments/1rof0ia/brian_thomas_jr_unlikely_to_be_traded_by_the/",
      "https://www.reddit.com/r/DynastyFF/comments/1rpb9w6/the_jaguars_are_entertaining_offers_for_wr_brian/"
    ],
    "article_count": 3,
    "generated_at": "2026-03-13T15:07:43"
  },
  "00-0030506": {
    "player_name": "Travis Kelce",
    "summary": "Reports indicate the Chiefs plan to target Kenneth Walker and a Travis Kelce replacement in the 2026 NFL Draft.",
    "sources": [
      "https://www.reddit.com/r/DynastyFF/comments/1rmv3wp/chiefs_to_make_a_play_for_kenneth_walker_along/"
    ],
    "article_count": 1,
    "generated_at": "2026-03-13T15:07:43"
  },
  "00-0029604": {
    "player_name": "Kirk Cousins",
    "summary": "The Las Vegas Raiders are expected to show interest in Kirk Cousins as a veteran QB addition to help develop presumptive No. 1 pick Fernando Mendoza.",
    "sources": [
      "https://www.reddit.com/r/DynastyFF/comments/1rr5gdc/russini_the_las_vegas_raiders_are_expected_to/"
    ],
    "article_count": 1,
    "generated_at": "2026-03-13T15:07:43"
  },
  "00-0036252": {
    "player_name": "Michael Pittman Jr.",
    "summary": "Michael Pittman is being traded to the Pittsburgh Steelers.",
    "sources": [
      "https://www.reddit.com/r/DynastyFF/comments/1rp5d1f/trade_michael_pittman_is_being_traded_to_the/"
    ],
    "article_count": 1,
    "generated_at": "2026-03-13T15:07:43"
  },
  "00-0035710": {
    "player_name": "Daniel Jones",
    "summary": "The Colts and QB Daniel Jones are finalizing a 2-year, $88M deal that can be worth up to $100M with incentives, including $60M guaranteed.",
    "sources": [
      "https://www.reddit.com/r/DynastyFF/comments/1rqwrrn/compensation_update_the_colts_and_qb_daniel_jones/",
      "https://www.reddit.com/r/DynastyFF/comments/1rjzz4h/news_the_colts_are_placing_the_transition_tag_on/"
    ],
    "article_count": 2,
    "generated_at": "2026-03-13T15:07:45"
  },
  "00-0038543": {
    "player_name": "Jaxon Smith-Njigba",
    "summary": "The Seahawks are unlikely to use their franchise tag on running back Kenneth Walker. The team has multiple free agents they want to retain and also plan to try to extend WR Jaxon Smith-Njigba.",
    "sources": [
      "https://www.reddit.com/r/DynastyFF/comments/1r74z0d/its_unlikely_the_seahawks_will_use_their/"
    ],
    "article_count": 1,
    "generated_at": "2026-03-13T15:07:45"
  },
  "00-0030565": {
    "player_name": "Geno Smith",
    "summary": "Geno Smith has been released by the Las Vegas Raiders.",
    "sources": [
      "https://www.reddit.com/r/DynastyFF/comments/1rmi35b/geno_smith_released_by_the_raiders/"
    ],
    "article_count": 1,
    "generated_at": "2026-03-13T15:07:45"
  },
  "00-0036212": {
    "player_name": "Tua Tagovailoa",
    "summary": "The Dolphins are releasing QB Tua Tagovailoa with a post-June 1 designation, resulting in an NFL-record $99 million in dead money split over two years, as new GM Jon-Eric Sullivan and HC Jeff Hafley get a fresh start at quarterback.",
    "sources": [
      "https://www.reddit.com/r/DynastyFF/comments/1royprm/sources_the_dolphins_are_releasing_qb_tua/"
    ],
    "article_count": 1,
    "generated_at": "2026-03-13T15:07:45"
  },
  "00-0033293": {
    "player_name": "Aaron Jones Sr.",
    "summary": "The Vikings and RB Aaron Jones have agreed to a revised contract to keep him in Minnesota for the 2026 season.",
    "sources": [
      "https://www.reddit.com/r/DynastyFF/comments/1rr2n9m/pelissero_the_vikings_and_rb_aaron_jones_have/"
    ],
    "article_count": 1,
    "generated_at": "2026-03-13T15:07:45"
  },
  "00-0035719": {
    "player_name": "Deebo Samuel",
    "summary": "Deebo Samuel is not expected to return to the Commanders, according to Matthew Berry.",
    "sources": [
      "https://www.reddit.com/r/DynastyFF/comments/1rj1xyp/deebo_samuel_not_expected_to_return_to_commanders/"
    ],
    "article_count": 1,
    "generated_at": "2026-03-13T15:07:45"
  },
  "00-0036261": {
    "player_name": "Brandon Aiyuk",
    "summary": "The 49ers plan to release wide receiver Brandon Aiyuk, which could happen as soon as today, per Nick Wagoner.",
    "sources": [
      "https://www.reddit.com/r/DynastyFF/comments/1rqz1hs/49ers_plan_to_release_brandon_aiyuk_per_nick/"
    ],
    "article_count": 1,
    "generated_at": "2026-03-13T15:07:45"
  },
  "00-0037837": {
    "player_name": "Calvin Austin III",
    "summary": "WR Calvin Austin is signing a one-year deal worth up to $4.5M with the New York Giants.",
    "sources": [
      "https://www.reddit.com/r/DynastyFF/comments/1rs4t7e/adam_schefter_wr_calvin_austin_is_signing_a/"
    ],
    "article_count": 1,
    "generated_at": "2026-03-13T15:38:59"
  },
  "00-0036849": {
    "player_name": "Tutu Atwell",
    "summary": "The Dolphins are signing former Rams free-agent wide receiver Tutu Atwell to a one-year deal. Atwell is from Miami and returns to his hometown.",
    "sources": [
      "https://www.reddit.com/r/DynastyFF/comments/1rs2ic3/adam_schefter_dolphins_are_signing_former_rams/"
    ],
    "article_count": 1,
    "generated_at": "2026-03-13T15:38:59"
  },
  "00-0038794": {
    "player_name": "Jaleel McLaughlin",
    "summary": "The Broncos have agreed to a 1-year deal to bring back versatile RB Jaleel McLaughlin.",
    "sources": [
      "https://www.reddit.com/r/DynastyFF/comments/1rsta39/the_broncos_have_agreed_to_terms_to_bring_back/"
    ],
    "article_count": 1,
    "generated_at": "2026-03-13T15:38:59"
  },
  "00-0035676": {
    "player_name": "A.J. Brown",
    "summary": "The New England Patriots and Los Angeles Rams are reportedly making strong pushes to acquire Eagles WR A.J. Brown.",
    "sources": [
      "https://www.reddit.com/r/DynastyFF/comments/1rswuip/russini_the_same_two_teams_the_new_england/"
    ],
    "article_count": 1,
    "generated_at": "2026-03-13T15:38:59"
  }
}